{
    "7e382157-b1bc-406d-b17b-facba43b716e": {
        "chain": "Ethereum",
        "project": "aave-v3",
        "symbol": "WBTC",
        "tvlUsd": 1997475017,
        "apyBase": 0.00536,
        "apyReward": null,
        "apy": 0.00536,
        "rewardTokens": null,
        "pool": "7e382157-b1bc-406d-b17b-facba43b716e",
        "apyPct1D": -3e-05,
        "apyPct7D": -0.00041,
        "apyPct30D": -0.00074,
        "stablecoin": false,
        "ilRisk": "no",
        "exposure": "single",
        "predictions": {
            "predictedClass": "Stable/Up",
            "predictedProbability": 80,
            "binnedConfidence": 3
        },
        "poolMeta": null,
        "mu": 0.06968,
        "sigma": 0.00584,
        "count": 1224,
        "outlier": false,
        "underlyingTokens": [
            "0x2260FAC5E5542a773Aa44fBCfeDf7C193bc2C599"
        ],
        "il7d": null,
        "apyBase7d": null,
        "apyMean30d": 0.00581,
        "volumeUsd1d": null,
        "volumeUsd7d": null,
        "apyBaseInception": null
    },
    "f981a304-bb6c-45b8-b0c5-fd2f515ad23a": {
        "chain": "Ethereum",
        "project": "aave-v3",
        "symbol": "USDT",
        "tvlUsd": 742301858,
        "apyBase": 2.11722,
        "apyReward": null,
        "apy": 2.11722,
        "rewardTokens": null,
        "pool": "f981a304-bb6c-45b8-b0c5-fd2f515ad23a",
        "apyPct1D": -0.27012,
        "apyPct7D": -0.57636,
        "apyPct30D": -0.57342,
        "stablecoin": true,
        "ilRisk": "no",
        "exposure": "single",
        "predictions": {
            "predictedClass": "Stable/Up",
            "predictedProbability": 80,
            "binnedConfidence": 3
        },
        "poolMeta": null,
        "mu": 4.49954,
        "sigma": 0.17162,
        "count": 1214,
        "outlier": false,
        "underlyingTokens": [
            "0xdAC17F958D2ee523a2206206994597C13D831ec7"
        ],
        "il7d": null,
        "apyBase7d": null,
        "apyMean30d": 2.58597,
        "volumeUsd1d": null,
        "volumeUsd7d": null,
        "apyBaseInception": null
    },
    "aa70268e-4b52-42bf-a116-608b370f9501": {
        "chain": "Ethereum",
        "project": "aave-v3",
        "symbol": "USDC",
        "tvlUsd": 226438998,
        "apyBase": 3.08304,
        "apyReward": null,
        "apy": 3.08304,
        "rewardTokens": null,
        "pool": "aa70268e-4b52-42bf-a116-608b370f9501",
        "apyPct1D": -0.00686,
        "apyPct7D": 0.01911,
        "apyPct30D": -0.2168,
        "stablecoin": true,
        "ilRisk": "no",
        "exposure": "single",
        "predictions": {
            "predictedClass": "Stable/Up",
            "predictedProbability": 57.99999999999999,
            "binnedConfidence": 1
        },
        "poolMeta": null,
        "mu": 4.77787,
        "sigma": 0.15916,
        "count": 1224,
        "outlier": false,
        "underlyingTokens": [
            "0xA0b86991c6218b36c1d19D4a2e9Eb0cE3606eB48"
        ],
        "il7d": null,
        "apyBase7d": null,
        "apyMean30d": 3.56008,
        "volumeUsd1d": null,
        "volumeUsd7d": null,
        "apyBaseInception": null
    },
    "569ab5a6-76e4-46a6-abb6-b12be4197e31": {
        "chain": "Plasma",
        "project": "aave-v3",
        "symbol": "SYRUPUSDT",
        "tvlUsd": 195908261,
        "apyBase": 0,
        "apyReward": null,
        "apy": 0,
        "rewardTokens": null,
        "pool": "569ab5a6-76e4-46a6-abb6-b12be4197e31",
        "apyPct1D": 0,
        "apyPct7D": 0,
        "apyPct30D": 0,
        "stablecoin": true,
        "ilRisk": "no",
        "exposure": "single",
        "predictions": {
            "predictedClass": null,
            "predictedProbability": null,
            "binnedConfidence": null
        },
        "poolMeta": null,
        "mu": 0,
        "sigma": 0,
        "count": 237,
        "outlier": false,
        "underlyingTokens": [
            "0xC4374775489CB9C56003BF2C9b12495fC64F0771"
        ],
        "il7d": null,
        "apyBase7d": null,
        "apyMean30d": 0,
        "volumeUsd1d": null,
        "volumeUsd7d": null,
        "apyBaseInception": null
    },
    "7c5e69a4-2430-4fa2-b7cb-857f79d7d1bf": {
        "chain": "Arbitrum",
        "project": "aave-v3",
        "symbol": "WBTC",
        "tvlUsd": 165488976,
        "apyBase": 0.0426,
        "apyReward": null,
        "apy": 0.0426,
        "rewardTokens": null,
        "pool": "7c5e69a4-2430-4fa2-b7cb-857f79d7d1bf",
        "apyPct1D": -0.00029,
        "apyPct7D": -5e-05,
        "apyPct30D": -0.00394,
        "stablecoin": false,
        "ilRisk": "no",
        "exposure": "single",
        "predictions": {
            "predictedClass": "Stable/Up",
            "predictedProbability": 82,
            "binnedConfidence": 3
        },
        "poolMeta": null,
        "mu": 0.13619,
        "sigma": 0.01193,
        "count": 1407,
        "outlier": false,
        "underlyingTokens": [
            "0x2f2a2543B76A4166549F7aaB2e75Bef0aefC5B0f"
        ],
        "il7d": null,
        "apyBase7d": null,
        "apyMean30d": 0.04604,
        "volumeUsd1d": null,
        "volumeUsd7d": null,
        "apyBaseInception": null
    },
    "e338c687-a5d8-4abf-bc04-127990811b0a": {
        "chain": "Plasma",
        "project": "aave-v3",
        "symbol": "USDT0",
        "tvlUsd": 101974801,
        "apyBase": 3.08143,
        "apyReward": 0.87875,
        "apy": 3.96018,
        "rewardTokens": [
            "0x6100E367285b01F48D07953803A2d8dCA5D19873"
        ],
        "pool": "e338c687-a5d8-4abf-bc04-127990811b0a",
        "apyPct1D": -0.48842,
        "apyPct7D": -0.41619,
        "apyPct30D": -2.04874,
        "stablecoin": true,
        "ilRisk": "no",
        "exposure": "single",
        "predictions": {
            "predictedClass": "Stable/Up",
            "predictedProbability": 52,
            "binnedConfidence": 1
        },
        "poolMeta": null,
        "mu": 3.71813,
        "sigma": 0.06327,
        "count": 262,
        "outlier": false,
        "underlyingTokens": [
            "0xB8CE59FC3717ada4C02eaDF9682A9e934F625ebb"
        ],
        "il7d": null,
        "apyBase7d": null,
        "apyMean30d": 4.46122,
        "volumeUsd1d": null,
        "volumeUsd7d": null,
        "apyBaseInception": null
    },
    "4dfb0ee0-6fa3-4b8b-83f7-b92e83f5242f": {
        "chain": "Mantle",
        "project": "aave-v3",
        "symbol": "SYRUPUSDT",
        "tvlUsd": 90409464,
        "apyBase": 0,
        "apyReward": null,
        "apy": 0,
        "rewardTokens": null,
        "pool": "4dfb0ee0-6fa3-4b8b-83f7-b92e83f5242f",
        "apyPct1D": 0,
        "apyPct7D": 0,
        "apyPct30D": 0,
        "stablecoin": true,
        "ilRisk": "no",
        "exposure": "single",
        "predictions": {
            "predictedClass": null,
            "predictedProbability": null,
            "binnedConfidence": null
        },
        "poolMeta": null,
        "mu": 0,
        "sigma": 0,
        "count": 78,
        "outlier": false,
        "underlyingTokens": [
            "0x051665f2455116e929b9972c36d23070F5054Ce0"
        ],
        "il7d": null,
        "apyBase7d": null,
        "apyMean30d": 0,
        "volumeUsd1d": null,
        "volumeUsd7d": null,
        "apyBaseInception": null
    },
    "a90d554a-b548-4f50-b03e-9dcb724b7777": {
        "chain": "Ethereum",
        "project": "aave-v3",
        "symbol": "USDT",
        "tvlUsd": 86053867,
        "apyBase": 2.11722,
        "apyReward": 4.08,
        "apy": 6.19722,
        "rewardTokens": [
            "0x23878914EFE38d27C4D67Ab83ed1b93A74D4086a"
        ],
        "pool": "a90d554a-b548-4f50-b03e-9dcb724b7777",
        "apyPct1D": -0.28012,
        "apyPct7D": -0.62636,
        "apyPct30D": -1.04342,
        "stablecoin": true,
        "ilRisk": "no",
        "exposure": "single",
        "predictions": {
            "predictedClass": "Down",
            "predictedProbability": 56.99999999999999,
            "binnedConfidence": 1
        },
        "poolMeta": "Umbrella",
        "mu": 6.63905,
        "sigma": 0.03818,
        "count": 32,
        "outlier": false,
        "underlyingTokens": [
            "0x7Bc3485026Ac48b6cf9BaF0A377477Fff5703Af8"
        ],
        "il7d": null,
        "apyBase7d": null,
        "apyMean30d": 6.61158,
        "volumeUsd1d": null,
        "volumeUsd7d": null,
        "apyBaseInception": null
    },
    "6f00d46b-8735-49ae-9ced-2a0fccc56ad0": {
        "chain": "Ethereum",
        "project": "aave-v3",
        "symbol": "USDC",
        "tvlUsd": 56289494,
        "apyBase": 3.08304,
        "apyReward": 4,
        "apy": 7.08304,
        "rewardTokens": [
            "0x98C23E9d8f34FEFb1B7BD6a91B7FF122F4e16F5c"
        ],
        "pool": "6f00d46b-8735-49ae-9ced-2a0fccc56ad0",
        "apyPct1D": -0.02686,
        "apyPct7D": -0.19089,
        "apyPct30D": -0.6968,
        "stablecoin": true,
        "ilRisk": "no",
        "exposure": "single",
        "predictions": {
            "predictedClass": "Stable/Up",
            "predictedProbability": 57.99999999999999,
            "binnedConfidence": 1
        },
        "poolMeta": "Umbrella",
        "mu": 7.48685,
        "sigma": 0.0481,
        "count": 32,
        "outlier": false,
        "underlyingTokens": [
            "0xD4fa2D31b7968E448877f69A96DE69f5de8cD23E"
        ],
        "il7d": null,
        "apyBase7d": null,
        "apyMean30d": 7.68778,
        "volumeUsd1d": null,
        "volumeUsd7d": null,
        "apyBaseInception": null
    },
    "58d18059-f1d1-45ed-acd3-f386e98cc506": {
        "chain": "Polygon",
        "project": "aave-v3",
        "symbol": "WBTC",
        "tvlUsd": 51494872,
        "apyBase": 0.01849,
        "apyReward": null,
        "apy": 0.01849,
        "rewardTokens": null,
        "pool": "58d18059-f1d1-45ed-acd3-f386e98cc506",
        "apyPct1D": -0.00108,
        "apyPct7D": -0.00071,
        "apyPct30D": -0.00135,
        "stablecoin": false,
        "ilRisk": "no",
        "exposure": "single",
        "predictions": {
            "predictedClass": "Stable/Up",
            "predictedProbability": 73,
            "binnedConfidence": 2
        },
        "poolMeta": null,
        "mu": 0.03336,
        "sigma": 0.0085,
        "count": 1407,
        "outlier": false,
        "underlyingTokens": [
            "0x1BFD67037B42Cf73acF2047067bd4F2C47D9BfD6"
        ],
        "il7d": null,
        "apyBase7d": null,
        "apyMean30d": 0.01907,
        "volumeUsd1d": null,
        "volumeUsd7d": null,
        "apyBaseInception": null
    },
    "47da0cdd-7b1d-4927-9545-20b53b73afa8": {
        "chain": "Mantle",
        "project": "aave-v3",
        "symbol": "USDT0",
        "tvlUsd": 48481164,
        "apyBase": 2.56832,
        "apyReward": 1.32107,
        "apy": 3.88939,
        "rewardTokens": [
            "0x09E4C43B7Ce78AC58fF6A920f1fD5D84a7975f78"
        ],
        "pool": "47da0cdd-7b1d-4927-9545-20b53b73afa8",
        "apyPct1D": -0.79936,
        "apyPct7D": -1.14826,
        "apyPct30D": -1.26551,
        "stablecoin": true,
        "ilRisk": "no",
        "exposure": "single",
        "predictions": {
            "predictedClass": "Down",
            "predictedProbability": 65,
            "binnedConfidence": 2
        },
        "poolMeta": null,
        "mu": 4.47174,
        "sigma": 0.10535,
        "count": 77,
        "outlier": false,
        "underlyingTokens": [
            "0x779Ded0c9e1022225f8E0630b35a9b54bE713736"
        ],
        "il7d": null,
        "apyBase7d": null,
        "apyMean30d": 5.11222,
        "volumeUsd1d": null,
        "volumeUsd7d": null,
        "apyBaseInception": null
    },
    "d9fa8e14-0447-4207-9ae8-7810199dfa1f": {
        "chain": "Arbitrum",
        "project": "aave-v3",
        "symbol": "USDC",
        "tvlUsd": 47204508,
        "apyBase": 2.19792,
        "apyReward": null,
        "apy": 2.19792,
        "rewardTokens": null,
        "pool": "d9fa8e14-0447-4207-9ae8-7810199dfa1f",
        "apyPct1D": 0.02365,
        "apyPct7D": 0.12963,
        "apyPct30D": -0.75989,
        "stablecoin": true,
        "ilRisk": "no",
        "exposure": "single",
        "predictions": {
            "predictedClass": "Stable/Up",
            "predictedProbability": 90,
            "binnedConfidence": 3
        },
        "poolMeta": null,
        "mu": 5.1309,
        "sigma": 0.16593,
        "count": 1083,
        "outlier": false,
        "underlyingTokens": [
            "0xaf88d065e77c8cC2239327C5EDb3A432268e5831"
        ],
        "il7d": null,
        "apyBase7d": null,
        "apyMean30d": 2.55116,
        "volumeUsd1d": null,
        "volumeUsd7d": null,
        "apyBaseInception": null
    },
    "f9258dd3-f50a-4ea3-8501-49b4b2603a5f": {
        "chain": "Ethereum",
        "project": "aave-v4",
        "symbol": "WBTC",
        "tvlUsd": 28940407,
        "apyBase": 0.00105,
        "apyReward": null,
        "apy": 0.00105,
        "rewardTokens": null,
        "pool": "f9258dd3-f50a-4ea3-8501-49b4b2603a5f",
        "apyPct1D": 0,
        "apyPct7D": -0.00345,
        "apyPct30D": -0.00383,
        "stablecoin": false,
        "ilRisk": "no",
        "exposure": "single",
        "predictions": {
            "predictedClass": "Stable/Up",
            "predictedProbability": 78,
            "binnedConfidence": 3
        },
        "poolMeta": "Core",
        "mu": 0.00643,
        "sigma": 0.00021,
        "count": 78,
        "outlier": false,
        "underlyingTokens": [
            "0x2260FAC5E5542a773Aa44fBCfeDf7C193bc2C599"
        ],
        "il7d": null,
        "apyBase7d": null,
        "apyMean30d": 0.00482,
        "volumeUsd1d": null,
        "volumeUsd7d": null,
        "apyBaseInception": null
    },
    "7e0661bf-8cf3-45e6-9424-31916d4c7b84": {
        "chain": "Base",
        "project": "aave-v3",
        "symbol": "USDC",
        "tvlUsd": 26967310,
        "apyBase": 3.22147,
        "apyReward": null,
        "apy": 3.22147,
        "rewardTokens": null,
        "pool": "7e0661bf-8cf3-45e6-9424-31916d4c7b84",
        "apyPct1D": 0.03167,
        "apyPct7D": 0.0593,
        "apyPct30D": 0.32372,
        "stablecoin": true,
        "ilRisk": "no",
        "exposure": "single",
        "predictions": {
            "predictedClass": "Stable/Up",
            "predictedProbability": 66,
            "binnedConfidence": 2
        },
        "poolMeta": null,
        "mu": 4.92094,
        "sigma": 0.13012,
        "count": 829,
        "outlier": false,
        "underlyingTokens": [
            "0x833589fCD6eDb6E08f4c7C32D4f71b54bdA02913"
        ],
        "il7d": null,
        "apyBase7d": null,
        "apyMean30d": 3.14835,
        "volumeUsd1d": null,
        "volumeUsd7d": null,
        "apyBaseInception": null
    },
    "baee0253-eb6e-4a08-a579-a2acd4f034b2": {
        "chain": "Ethereum",
        "project": "aave-v3",
        "symbol": "USDTB",
        "tvlUsd": 21400147,
        "apyBase": 2.51171,
        "apyReward": 3.4,
        "apy": 5.91171,
        "rewardTokens": [
            "0x04EADd7B10ea9a484c60860aea7A7C0AEc09B9F0"
        ],
        "pool": "baee0253-eb6e-4a08-a579-a2acd4f034b2",
        "apyPct1D": 0.15217,
        "apyPct7D": 0.15344,
        "apyPct30D": 0.1322,
        "stablecoin": true,
        "ilRisk": "no",
        "exposure": "single",
        "predictions": {
            "predictedClass": "Down",
            "predictedProbability": 75,
            "binnedConfidence": 3
        },
        "poolMeta": null,
        "mu": 1.97129,
        "sigma": 0.08247,
        "count": 377,
        "outlier": false,
        "underlyingTokens": [
            "0xC139190F447e929f090Edeb554D95AbB8b18aC1C"
        ],
        "il7d": null,
        "apyBase7d": null,
        "apyMean30d": 5.50659,
        "volumeUsd1d": null,
        "volumeUsd7d": null,
        "apyBaseInception": null
    },
    "3665ee7e-6c5d-49d9-abb7-c47ab5d9d4ac": {
        "chain": "Ethereum",
        "project": "aave-v3",
        "symbol": "DAI",
        "tvlUsd": 12715879,
        "apyBase": 3.16536,
        "apyReward": null,
        "apy": 3.16536,
        "rewardTokens": null,
        "pool": "3665ee7e-6c5d-49d9-abb7-c47ab5d9d4ac",
        "apyPct1D": 0.07807,
        "apyPct7D": -2.51046,
        "apyPct30D": 0.42356,
        "stablecoin": true,
        "ilRisk": "no",
        "exposure": "single",
        "predictions": {
            "predictedClass": "Stable/Up",
            "predictedProbability": 67,
            "binnedConfidence": 2
        },
        "poolMeta": null,
        "mu": 4.45731,
        "sigma": 0.17204,
        "count": 1224,
        "outlier": false,
        "underlyingTokens": [
            "0x6B175474E89094C44Da98b954EedeAC495271d0F"
        ],
        "il7d": null,
        "apyBase7d": null,
        "apyMean30d": 2.69964,
        "volumeUsd1d": null,
        "volumeUsd7d": null,
        "apyBaseInception": null
    },
    "29be6a85-414f-4a66-b075-98863278912a": {
        "chain": "BSC",
        "project": "aave-v3",
        "symbol": "USDT",
        "tvlUsd": 12393565,
        "apyBase": 2.40337,
        "apyReward": null,
        "apy": 2.40337,
        "rewardTokens": null,
        "pool": "29be6a85-414f-4a66-b075-98863278912a",
        "apyPct1D": -0.15511,
        "apyPct7D": 0.5492,
        "apyPct30D": -0.14598,
        "stablecoin": true,
        "ilRisk": "no",
        "exposure": "single",
        "predictions": {
            "predictedClass": "Stable/Up",
            "predictedProbability": 93,
            "binnedConfidence": 3
        },
        "poolMeta": null,
        "mu": 3.97583,
        "sigma": 0.10905,
        "count": 737,
        "outlier": false,
        "underlyingTokens": [
            "0x55d398326f99059fF775485246999027B3197955"
        ],
        "il7d": null,
        "apyBase7d": null,
        "apyMean30d": 2.29919,
        "volumeUsd1d": null,
        "volumeUsd7d": null,
        "apyBaseInception": null
    },
    "974b8732-2dce-4a46-8204-7f9e6b7efb71": {
        "chain": "Base",
        "project": "aave-v3",
        "symbol": "SYRUPUSDC",
        "tvlUsd": 12348028,
        "apyBase": 0,
        "apyReward": null,
        "apy": 0,
        "rewardTokens": null,
        "pool": "974b8732-2dce-4a46-8204-7f9e6b7efb71",
        "apyPct1D": 0,
        "apyPct7D": 0,
        "apyPct30D": 0,
        "stablecoin": true,
        "ilRisk": "no",
        "exposure": "single",
        "predictions": {
            "predictedClass": null,
            "predictedProbability": null,
            "binnedConfidence": null
        },
        "poolMeta": null,
        "mu": 0,
        "sigma": 0,
        "count": 143,
        "outlier": false,
        "underlyingTokens": [
            "0x660975730059246A68521a3e2FBD4740173100f5"
        ],
        "il7d": null,
        "apyBase7d": null,
        "apyMean30d": 0,
        "volumeUsd1d": null,
        "volumeUsd7d": null,
        "apyBaseInception": null
    },
    "7e7821a2-3d20-4ae7-9c3d-04cd57904555": {
        "chain": "Polygon",
        "project": "aave-v3",
        "symbol": "USDT0",
        "tvlUsd": 12256071,
        "apyBase": 2.8107,
        "apyReward": null,
        "apy": 2.8107,
        "rewardTokens": null,
        "pool": "7e7821a2-3d20-4ae7-9c3d-04cd57904555",
        "apyPct1D": -0.03894,
        "apyPct7D": -0.03145,
        "apyPct30D": -0.01308,
        "stablecoin": true,
        "ilRisk": "no",
        "exposure": "single",
        "predictions": {
            "predictedClass": "Stable/Up",
            "predictedProbability": 87,
            "binnedConfidence": 3
        },
        "poolMeta": null,
        "mu": 4.57011,
        "sigma": 0.165,
        "count": 1402,
        "outlier": false,
        "underlyingTokens": [
            "0xc2132D05D31c914a87C6611C10748AEb04B58e8F"
        ],
        "il7d": null,
        "apyBase7d": null,
        "apyMean30d": 2.83436,
        "volumeUsd1d": null,
        "volumeUsd7d": null,
        "apyBaseInception": null
    },
    "e053590b-54f1-40aa-ae0d-14e701ca734c": {
        "chain": "OP Mainnet",
        "project": "aave-v3",
        "symbol": "WBTC",
        "tvlUsd": 11997592,
        "apyBase": 0.02338,
        "apyReward": null,
        "apy": 0.02338,
        "rewardTokens": null,
        "pool": "e053590b-54f1-40aa-ae0d-14e701ca734c",
        "apyPct1D": 0.00019,
        "apyPct7D": -0.00055,
        "apyPct30D": -0.00182,
        "stablecoin": false,
        "ilRisk": "no",
        "exposure": "single",
        "predictions": {
            "predictedClass": "Stable/Up",
            "predictedProbability": 85,
            "binnedConfidence": 3
        },
        "poolMeta": null,
        "mu": 0.18882,
        "sigma": 0.03219,
        "count": 1407,
        "outlier": false,
        "underlyingTokens": [
            "0x68f180fcCe6836688e9084f035309E29Bf0A2095"
        ],
        "il7d": null,
        "apyBase7d": null,
        "apyMean30d": 0.02449,
        "volumeUsd1d": null,
        "volumeUsd7d": null,
        "apyBaseInception": null
    },
    "1b8b4cdb-0728-42a8-bf13-2c8fea7427ee": {
        "chain": "Polygon",
        "project": "aave-v3",
        "symbol": "USDC",
        "tvlUsd": 11820305,
        "apyBase": 2.8752,
        "apyReward": null,
        "apy": 2.8752,
        "rewardTokens": null,
        "pool": "1b8b4cdb-0728-42a8-bf13-2c8fea7427ee",
        "apyPct1D": -0.00805,
        "apyPct7D": -0.04539,
        "apyPct30D": -0.29022,
        "stablecoin": true,
        "ilRisk": "no",
        "exposure": "single",
        "predictions": {
            "predictedClass": "Stable/Up",
            "predictedProbability": 87,
            "binnedConfidence": 3
        },
        "poolMeta": null,
        "mu": 5.18033,
        "sigma": 0.15197,
        "count": 907,
        "outlier": false,
        "underlyingTokens": [
            "0x3c499c542cEF5E3811e1192ce70d8cC03d5c3359"
        ],
        "il7d": null,
        "apyBase7d": null,
        "apyMean30d": 3.17617,
        "volumeUsd1d": null,
        "volumeUsd7d": null,
        "apyBaseInception": null
    },
    "a79fdd93-2747-43ee-bf53-0c372192964d": {
        "chain": "Ethereum",
        "project": "aave-v3",
        "symbol": "SYRUPUSDT",
        "tvlUsd": 10507326,
        "apyBase": 0,
        "apyReward": null,
        "apy": 0,
        "rewardTokens": null,
        "pool": "a79fdd93-2747-43ee-bf53-0c372192964d",
        "apyPct1D": 0,
        "apyPct7D": 0,
        "apyPct30D": 0,
        "stablecoin": true,
        "ilRisk": "no",
        "exposure": "single",
        "predictions": {
            "predictedClass": null,
            "predictedProbability": null,
            "binnedConfidence": null
        },
        "poolMeta": null,
        "mu": 0,
        "sigma": 0,
        "count": 196,
        "outlier": false,
        "underlyingTokens": [
            "0x356B8d89c1e1239Cbbb9dE4815c39A1474d5BA7D"
        ],
        "il7d": null,
        "apyBase7d": null,
        "apyMean30d": 0,
        "volumeUsd1d": null,
        "volumeUsd7d": null,
        "apyBaseInception": null
    },
    "32f04d80-25f9-439f-838d-3b15becf2d21": {
        "chain": "Gnosis",
        "project": "aave-v3",
        "symbol": "SDAI",
        "tvlUsd": 9303078,
        "apyBase": 0,
        "apyReward": null,
        "apy": 0,
        "rewardTokens": null,
        "pool": "32f04d80-25f9-439f-838d-3b15becf2d21",
        "apyPct1D": 0,
        "apyPct7D": 0,
        "apyPct30D": 0,
        "stablecoin": true,
        "ilRisk": "no",
        "exposure": "single",
        "predictions": {
            "predictedClass": null,
            "predictedProbability": null,
            "binnedConfidence": null
        },
        "poolMeta": null,
        "mu": 0,
        "sigma": 0,
        "count": 872,
        "outlier": false,
        "underlyingTokens": [
            "0xaf204776c7245bF4147c2612BF6e5972Ee483701"
        ],
        "il7d": null,
        "apyBase7d": null,
        "apyMean30d": 0,
        "volumeUsd1d": null,
        "volumeUsd7d": null,
        "apyBaseInception": null
    },
    "0925bef8-3d9f-4ad7-81e2-34feec9d3d29": {
        "chain": "Ethereum",
        "project": "aave-v4",
        "symbol": "WBTC",
        "tvlUsd": 8081085,
        "apyBase": 0,
        "apyReward": null,
        "apy": 0,
        "rewardTokens": null,
        "pool": "0925bef8-3d9f-4ad7-81e2-34feec9d3d29",
        "apyPct1D": 0,
        "apyPct7D": 0,
        "apyPct30D": 0,
        "stablecoin": false,
        "ilRisk": "no",
        "exposure": "single",
        "predictions": {
            "predictedClass": null,
            "predictedProbability": null,
            "binnedConfidence": null
        },
        "poolMeta": "Prime",
        "mu": 0,
        "sigma": 0,
        "count": 79,
        "outlier": false,
        "underlyingTokens": [
            "0x2260FAC5E5542a773Aa44fBCfeDf7C193bc2C599"
        ],
        "il7d": null,
        "apyBase7d": null,
        "apyMean30d": 0,
        "volumeUsd1d": null,
        "volumeUsd7d": null,
        "apyBaseInception": null
    },
    "15cf7c05-b5f0-4bde-8745-a791528c4381": {
        "chain": "BSC",
        "project": "aave-v3",
        "symbol": "USDC",
        "tvlUsd": 6485332,
        "apyBase": 1.71743,
        "apyReward": null,
        "apy": 1.71743,
        "rewardTokens": null,
        "pool": "15cf7c05-b5f0-4bde-8745-a791528c4381",
        "apyPct1D": -0.12154,
        "apyPct7D": -0.42897,
        "apyPct30D": -0.5011,
        "stablecoin": true,
        "ilRisk": "no",
        "exposure": "single",
        "predictions": {
            "predictedClass": "Stable/Up",
            "predictedProbability": 97,
            "binnedConfidence": 3
        },
        "poolMeta": null,
        "mu": 4.10232,
        "sigma": 0.1223,
        "count": 737,
        "outlier": false,
        "underlyingTokens": [
            "0x8AC76a51cc950d9822D68b83fE1Ad97B32Cd580d"
        ],
        "il7d": null,
        "apyBase7d": null,
        "apyMean30d": 2.30875,
        "volumeUsd1d": null,
        "volumeUsd7d": null,
        "apyBaseInception": null
    },
    "c4b05318-88af-4536-a834-f5fc8940d2d3": {
        "chain": "Avalanche",
        "project": "aave-v3",
        "symbol": "USDC",
        "tvlUsd": 6123401,
        "apyBase": 3.51529,
        "apyReward": null,
        "apy": 3.51529,
        "rewardTokens": null,
        "pool": "c4b05318-88af-4536-a834-f5fc8940d2d3",
        "apyPct1D": 0.13659,
        "apyPct7D": -0.75859,
        "apyPct30D": -2.05832,
        "stablecoin": true,
        "ilRisk": "no",
        "exposure": "single",
        "predictions": {
            "predictedClass": "Stable/Up",
            "predictedProbability": 77,
            "binnedConfidence": 3
        },
        "poolMeta": null,
        "mu": 4.35647,
        "sigma": 0.1858,
        "count": 1249,
        "outlier": false,
        "underlyingTokens": [
            "0xB97EF9Ef8734C71904D8002F8b6Bc66Dd9c48a6E"
        ],
        "il7d": null,
        "apyBase7d": null,
        "apyMean30d": 4.41096,
        "volumeUsd1d": null,
        "volumeUsd7d": null,
        "apyBaseInception": null
    },
    "e6692d08-85b6-4b50-952b-7c5c531862fe": {
        "chain": "Avalanche",
        "project": "aave-v3",
        "symbol": "USDT",
        "tvlUsd": 3101801,
        "apyBase": 3.16161,
        "apyReward": null,
        "apy": 3.16161,
        "rewardTokens": null,
        "pool": "e6692d08-85b6-4b50-952b-7c5c531862fe",
        "apyPct1D": -0.8948,
        "apyPct7D": -1.2097,
        "apyPct30D": -2.70089,
        "stablecoin": true,
        "ilRisk": "no",
        "exposure": "single",
        "predictions": {
            "predictedClass": "Stable/Up",
            "predictedProbability": 61,
            "binnedConfidence": 2
        },
        "poolMeta": null,
        "mu": 4.3225,
        "sigma": 0.18124,
        "count": 1249,
        "outlier": false,
        "underlyingTokens": [
            "0x9702230A8Ea53601f5cD2dc00fDBc13d4dF4A8c7"
        ],
        "il7d": null,
        "apyBase7d": null,
        "apyMean30d": 4.52451,
        "volumeUsd1d": null,
        "volumeUsd7d": null,
        "apyBaseInception": null
    },
    "27296bf9-617a-46e4-9d6d-eefc71e9e0b6": {
        "chain": "Ethereum",
        "project": "aave-v3",
        "symbol": "USDC",
        "tvlUsd": 3054305,
        "apyBase": 2.56953,
        "apyReward": null,
        "apy": 2.56953,
        "rewardTokens": null,
        "pool": "27296bf9-617a-46e4-9d6d-eefc71e9e0b6",
        "apyPct1D": 0.4384,
        "apyPct7D": -0.49596,
        "apyPct30D": -0.73151,
        "stablecoin": true,
        "ilRisk": "no",
        "exposure": "single",
        "predictions": {
            "predictedClass": "Stable/Up",
            "predictedProbability": 53,
            "binnedConfidence": 1
        },
        "poolMeta": "Aave Horizon Market",
        "mu": 2.80008,
        "sigma": 0.03344,
        "count": 139,
        "outlier": false,
        "underlyingTokens": [
            "0xA0b86991c6218b36c1d19D4a2e9Eb0cE3606eB48"
        ],
        "il7d": null,
        "apyBase7d": null,
        "apyMean30d": 2.70445,
        "volumeUsd1d": null,
        "volumeUsd7d": null,
        "apyBaseInception": null
    },
    "effcb4a4-4dcb-45e5-935d-f15542c13e6b": {
        "chain": "Ethereum",
        "project": "aave-v3",
        "symbol": "USDC",
        "tvlUsd": 2794767,
        "apyBase": 1.63631,
        "apyReward": null,
        "apy": 1.63631,
        "rewardTokens": null,
        "pool": "effcb4a4-4dcb-45e5-935d-f15542c13e6b",
        "apyPct1D": 0.00041,
        "apyPct7D": 0.2453,
        "apyPct30D": -1.71726,
        "stablecoin": true,
        "ilRisk": "no",
        "exposure": "single",
        "predictions": {
            "predictedClass": "Stable/Up",
            "predictedProbability": 93,
            "binnedConfidence": 3
        },
        "poolMeta": "Prime Instance",
        "mu": 4.25229,
        "sigma": 0.12516,
        "count": 586,
        "outlier": false,
        "underlyingTokens": [
            "0xA0b86991c6218b36c1d19D4a2e9Eb0cE3606eB48"
        ],
        "il7d": null,
        "apyBase7d": null,
        "apyMean30d": 2.73235,
        "volumeUsd1d": null,
        "volumeUsd7d": null,
        "apyBaseInception": null
    },
    "32cb38a5-b9b9-441a-bf07-8fab47b999d3": {
        "chain": "Mantle",
        "project": "aave-v3",
        "symbol": "USDC",
        "tvlUsd": 2292232,
        "apyBase": 2.61432,
        "apyReward": 2.59318,
        "apy": 5.20751,
        "rewardTokens": [
            "0x09E4C43B7Ce78AC58fF6A920f1fD5D84a7975f78"
        ],
        "pool": "32cb38a5-b9b9-441a-bf07-8fab47b999d3",
        "apyPct1D": -1.23449,
        "apyPct7D": -0.94066,
        "apyPct30D": -0.57744,
        "stablecoin": true,
        "ilRisk": "no",
        "exposure": "single",
        "predictions": {
            "predictedClass": "Down",
            "predictedProbability": 50,
            "binnedConfidence": 1
        },
        "poolMeta": null,
        "mu": 5.48538,
        "sigma": 0.1249,
        "count": 77,
        "outlier": false,
        "underlyingTokens": [
            "0x09Bc4E0D864854c6aFB6eB9A9cdF58aC190D0dF9"
        ],
        "il7d": null,
        "apyBase7d": null,
        "apyMean30d": 6.35314,
        "volumeUsd1d": null,
        "volumeUsd7d": null,
        "apyBaseInception": null
    },
    "0758c3b8-4ffb-4176-b0a9-f446e367db46": {
        "chain": "OP Mainnet",
        "project": "aave-v3",
        "symbol": "USDC",
        "tvlUsd": 2088663,
        "apyBase": 2.76917,
        "apyReward": null,
        "apy": 2.76917,
        "rewardTokens": null,
        "pool": "0758c3b8-4ffb-4176-b0a9-f446e367db46",
        "apyPct1D": 0.02857,
        "apyPct7D": 0.38616,
        "apyPct30D": -0.03721,
        "stablecoin": true,
        "ilRisk": "no",
        "exposure": "single",
        "predictions": {
            "predictedClass": "Stable/Up",
            "predictedProbability": 88,
            "binnedConfidence": 3
        },
        "poolMeta": null,
        "mu": 5.36629,
        "sigma": 0.18668,
        "count": 930,
        "outlier": false,
        "underlyingTokens": [
            "0x0b2C639c533813f4Aa9D7837CAf62653d097Ff85"
        ],
        "il7d": null,
        "apyBase7d": null,
        "apyMean30d": 2.72724,
        "volumeUsd1d": null,
        "volumeUsd7d": null,
        "apyBaseInception": null
    },
    "517f3a7a-a3b0-4af9-be8e-bcb0fb549744": {
        "chain": "Ethereum",
        "project": "aave-v4",
        "symbol": "USDT",
        "tvlUsd": 2079971,
        "apyBase": 2.07346,
        "apyReward": null,
        "apy": 2.07346,
        "rewardTokens": null,
        "pool": "517f3a7a-a3b0-4af9-be8e-bcb0fb549744",
        "apyPct1D": 0.00372,
        "apyPct7D": 0.80364,
        "apyPct30D": -1.14664,
        "stablecoin": true,
        "ilRisk": "no",
        "exposure": "single",
        "predictions": {
            "predictedClass": "Down",
            "predictedProbability": 50,
            "binnedConfidence": 1
        },
        "poolMeta": "Core",
        "mu": 2.25535,
        "sigma": 0.07082,
        "count": 79,
        "outlier": false,
        "underlyingTokens": [
            "0xdAC17F958D2ee523a2206206994597C13D831ec7"
        ],
        "il7d": null,
        "apyBase7d": null,
        "apyMean30d": 2.11653,
        "volumeUsd1d": null,
        "volumeUsd7d": null,
        "apyBaseInception": null
    },
    "a8e3d841-2788-4647-ad54-5a36fac451b1": {
        "chain": "Arbitrum",
        "project": "aave-v3",
        "symbol": "DAI",
        "tvlUsd": 1336046,
        "apyBase": 1.74055,
        "apyReward": null,
        "apy": 1.74055,
        "rewardTokens": null,
        "pool": "a8e3d841-2788-4647-ad54-5a36fac451b1",
        "apyPct1D": -0.00047,
        "apyPct7D": 0.01054,
        "apyPct30D": -0.51116,
        "stablecoin": true,
        "ilRisk": "no",
        "exposure": "single",
        "predictions": {
            "predictedClass": "Stable/Up",
            "predictedProbability": 86,
            "binnedConfidence": 3
        },
        "poolMeta": null,
        "mu": 4.1183,
        "sigma": 0.19429,
        "count": 1402,
        "outlier": false,
        "underlyingTokens": [
            "0xDA10009cBd5D07dd0CeCc66161FC93D7c9000da1"
        ],
        "il7d": null,
        "apyBase7d": null,
        "apyMean30d": 1.95654,
        "volumeUsd1d": null,
        "volumeUsd7d": null,
        "apyBaseInception": null
    },
    "461505e0-e631-4af0-b0e9-6a861d917939": {
        "chain": "Gnosis",
        "project": "aave-v3",
        "symbol": "USDC.E",
        "tvlUsd": 1282110,
        "apyBase": 2.46388,
        "apyReward": null,
        "apy": 2.46388,
        "rewardTokens": null,
        "pool": "461505e0-e631-4af0-b0e9-6a861d917939",
        "apyPct1D": -0.0021,
        "apyPct7D": 0.17846,
        "apyPct30D": 0.59876,
        "stablecoin": true,
        "ilRisk": "no",
        "exposure": "single",
        "predictions": {
            "predictedClass": "Stable/Up",
            "predictedProbability": 53,
            "binnedConfidence": 1
        },
        "poolMeta": null,
        "mu": 2.62216,
        "sigma": 0.04546,
        "count": 678,
        "outlier": false,
        "underlyingTokens": [
            "0x2a22f9c3b484c3629090FeED35F17Ff8F88f76F0"
        ],
        "il7d": null,
        "apyBase7d": null,
        "apyMean30d": 2.4031,
        "volumeUsd1d": null,
        "volumeUsd7d": null,
        "apyBaseInception": null
    },
    "24762515-822a-46af-927c-77a1dc449bd0": {
        "chain": "OP Mainnet",
        "project": "aave-v3",
        "symbol": "USDC",
        "tvlUsd": 919936,
        "apyBase": 0.35165,
        "apyReward": null,
        "apy": 0.35165,
        "rewardTokens": null,
        "pool": "24762515-822a-46af-927c-77a1dc449bd0",
        "apyPct1D": 4e-05,
        "apyPct7D": -0.03617,
        "apyPct30D": -1.63943,
        "stablecoin": true,
        "ilRisk": "no",
        "exposure": "single",
        "predictions": {
            "predictedClass": "Stable/Up",
            "predictedProbability": 87,
            "binnedConfidence": 3
        },
        "poolMeta": null,
        "mu": 3.38327,
        "sigma": 0.16025,
        "count": 1402,
        "outlier": false,
        "underlyingTokens": [
            "0x7F5c764cBc14f9669B88837ca1490cCa17c31607"
        ],
        "il7d": null,
        "apyBase7d": null,
        "apyMean30d": 1.06391,
        "volumeUsd1d": null,
        "volumeUsd7d": null,
        "apyBaseInception": null
    },
    "bde08c85-41c5-4d80-9bb1-0835a4352efa": {
        "chain": "OP Mainnet",
        "project": "aave-v3",
        "symbol": "USDT",
        "tvlUsd": 917992,
        "apyBase": 2.5475,
        "apyReward": null,
        "apy": 2.5475,
        "rewardTokens": null,
        "pool": "bde08c85-41c5-4d80-9bb1-0835a4352efa",
        "apyPct1D": -0.1493,
        "apyPct7D": 0.11791,
        "apyPct30D": -0.1995,
        "stablecoin": true,
        "ilRisk": "no",
        "exposure": "single",
        "predictions": {
            "predictedClass": "Stable/Up",
            "predictedProbability": 72,
            "binnedConfidence": 2
        },
        "poolMeta": null,
        "mu": 4.89938,
        "sigma": 0.21298,
        "count": 1402,
        "outlier": false,
        "underlyingTokens": [
            "0x94b008aA00579c1307B0EF2c499aD98a8ce58e58"
        ],
        "il7d": null,
        "apyBase7d": null,
        "apyMean30d": 2.50962,
        "volumeUsd1d": null,
        "volumeUsd7d": null,
        "apyBaseInception": null
    },
    "21091399-1187-4242-8e03-9b06032f9a8f": {
        "chain": "Gnosis",
        "project": "aave-v3",
        "symbol": "WXDAI",
        "tvlUsd": 864165,
        "apyBase": 0.89473,
        "apyReward": null,
        "apy": 0.89473,
        "rewardTokens": null,
        "pool": "21091399-1187-4242-8e03-9b06032f9a8f",
        "apyPct1D": -0.00375,
        "apyPct7D": 0.67046,
        "apyPct30D": -2.2459,
        "stablecoin": true,
        "ilRisk": "no",
        "exposure": "single",
        "predictions": {
            "predictedClass": "Stable/Up",
            "predictedProbability": 91,
            "binnedConfidence": 3
        },
        "poolMeta": null,
        "mu": 4.07987,
        "sigma": 0.11808,
        "count": 872,
        "outlier": false,
        "underlyingTokens": [
            "0xe91D153E0b41518A2Ce8Dd3D7944Fa863463a97d"
        ],
        "il7d": null,
        "apyBase7d": null,
        "apyMean30d": 1.07771,
        "volumeUsd1d": null,
        "volumeUsd7d": null,
        "apyBaseInception": null
    },
    "3e669ce8-74c5-4fc9-bf85-f40a924c6407": {
        "chain": "Avalanche",
        "project": "aave-v3",
        "symbol": "DAI.E",
        "tvlUsd": 777758,
        "apyBase": 2.51622,
        "apyReward": null,
        "apy": 2.51622,
        "rewardTokens": null,
        "pool": "3e669ce8-74c5-4fc9-bf85-f40a924c6407",
        "apyPct1D": 0.00756,
        "apyPct7D": -0.39231,
        "apyPct30D": -0.79103,
        "stablecoin": true,
        "ilRisk": "no",
        "exposure": "single",
        "predictions": {
            "predictedClass": "Stable/Up",
            "predictedProbability": 68,
            "binnedConfidence": 2
        },
        "poolMeta": null,
        "mu": 3.34163,
        "sigma": 0.15782,
        "count": 1250,
        "outlier": false,
        "underlyingTokens": [
            "0xd586E7F844cEa2F87f50152665BCbc2C279D8d70"
        ],
        "il7d": null,
        "apyBase7d": null,
        "apyMean30d": 3.01503,
        "volumeUsd1d": null,
        "volumeUsd7d": null,
        "apyBaseInception": null
    },
    "e68ecfb4-ba44-49e9-9626-31299405b520": {
        "chain": "Linea",
        "project": "aave-v3",
        "symbol": "WBTC",
        "tvlUsd": 742624,
        "apyBase": 0.06054,
        "apyReward": null,
        "apy": 0.06054,
        "rewardTokens": null,
        "pool": "e68ecfb4-ba44-49e9-9626-31299405b520",
        "apyPct1D": 0.00575,
        "apyPct7D": 0.01445,
        "apyPct30D": 0.01392,
        "stablecoin": false,
        "ilRisk": "no",
        "exposure": "single",
        "predictions": {
            "predictedClass": "Down",
            "predictedProbability": 53,
            "binnedConfidence": 1
        },
        "poolMeta": null,
        "mu": 0.04972,
        "sigma": 0.00398,
        "count": 464,
        "outlier": false,
        "underlyingTokens": [
            "0x3aAB2285ddcDdaD8edf438C1bAB47e1a9D05a9b4"
        ],
        "il7d": null,
        "apyBase7d": null,
        "apyMean30d": 0.05254,
        "volumeUsd1d": null,
        "volumeUsd7d": null,
        "apyBaseInception": null
    },
    "37b04faa-95bb-4ccb-9c4e-c70fa167342b": {
        "chain": "Polygon",
        "project": "aave-v3",
        "symbol": "USDC",
        "tvlUsd": 717339,
        "apyBase": 2.87252,
        "apyReward": null,
        "apy": 2.87252,
        "rewardTokens": null,
        "pool": "37b04faa-95bb-4ccb-9c4e-c70fa167342b",
        "apyPct1D": 0.00064,
        "apyPct7D": -0.00567,
        "apyPct30D": 0.09777,
        "stablecoin": true,
        "ilRisk": "no",
        "exposure": "single",
        "predictions": {
            "predictedClass": "Stable/Up",
            "predictedProbability": 69,
            "binnedConfidence": 2
        },
        "poolMeta": null,
        "mu": 3.95792,
        "sigma": 0.17278,
        "count": 1402,
        "outlier": false,
        "underlyingTokens": [
            "0x2791Bca1f2de4661ED88A30C99A7a9449Aa84174"
        ],
        "il7d": null,
        "apyBase7d": null,
        "apyMean30d": 2.92594,
        "volumeUsd1d": null,
        "volumeUsd7d": null,
        "apyBaseInception": null
    },
    "09f4aa6a-f06b-4635-ada0-5f0e334d41f0": {
        "chain": "Aptos",
        "project": "aave-v3",
        "symbol": "USDT",
        "tvlUsd": 625511,
        "apyBase": 1.69649,
        "apyReward": null,
        "apy": 1.69649,
        "rewardTokens": null,
        "pool": "09f4aa6a-f06b-4635-ada0-5f0e334d41f0",
        "apyPct1D": -0.00815,
        "apyPct7D": -0.0006,
        "apyPct30D": 0.69398,
        "stablecoin": true,
        "ilRisk": "no",
        "exposure": "single",
        "predictions": {
            "predictedClass": "Stable/Up",
            "predictedProbability": 66,
            "binnedConfidence": 2
        },
        "poolMeta": null,
        "mu": 1.50509,
        "sigma": 0.05602,
        "count": 91,
        "outlier": false,
        "underlyingTokens": [
            "0x357b0b74bc833e95a115ad22604854d6b0fca151cecd94111770e5d6ffc9dc2b"
        ],
        "il7d": null,
        "apyBase7d": null,
        "apyMean30d": 1.43845,
        "volumeUsd1d": null,
        "volumeUsd7d": null,
        "apyBaseInception": null
    },
    "c57bdc97-3100-41ff-845f-075363f6f5a4": {
        "chain": "Polygon",
        "project": "aave-v3",
        "symbol": "DAI",
        "tvlUsd": 599124,
        "apyBase": 5.11955,
        "apyReward": null,
        "apy": 5.11955,
        "rewardTokens": null,
        "pool": "c57bdc97-3100-41ff-845f-075363f6f5a4",
        "apyPct1D": 0.02894,
        "apyPct7D": -0.25628,
        "apyPct30D": 0.09257,
        "stablecoin": true,
        "ilRisk": "no",
        "exposure": "single",
        "predictions": {
            "predictedClass": "Down",
            "predictedProbability": 61,
            "binnedConfidence": 2
        },
        "poolMeta": null,
        "mu": 4.40323,
        "sigma": 0.17754,
        "count": 1402,
        "outlier": false,
        "underlyingTokens": [
            "0x8f3Cf7ad23Cd3CaDbD9735AFf958023239c6A063"
        ],
        "il7d": null,
        "apyBase7d": null,
        "apyMean30d": 5.01912,
        "volumeUsd1d": null,
        "volumeUsd7d": null,
        "apyBaseInception": null
    },
    "4ac1a968-68ab-4da8-87e3-8f1e15e3dae2": {
        "chain": "Ethereum",
        "project": "aave-v4",
        "symbol": "USDC",
        "tvlUsd": 558358,
        "apyBase": 3.23849,
        "apyReward": null,
        "apy": 3.23849,
        "rewardTokens": null,
        "pool": "4ac1a968-68ab-4da8-87e3-8f1e15e3dae2",
        "apyPct1D": -2.57724,
        "apyPct7D": 0.30241,
        "apyPct30D": 0.1871,
        "stablecoin": true,
        "ilRisk": "no",
        "exposure": "single",
        "predictions": {
            "predictedClass": "Down",
            "predictedProbability": 52,
            "binnedConfidence": 1
        },
        "poolMeta": "Core",
        "mu": 3.11431,
        "sigma": 0.10423,
        "count": 79,
        "outlier": false,
        "underlyingTokens": [
            "0xA0b86991c6218b36c1d19D4a2e9Eb0cE3606eB48"
        ],
        "il7d": null,
        "apyBase7d": null,
        "apyMean30d": 3.72939,
        "volumeUsd1d": null,
        "volumeUsd7d": null,
        "apyBaseInception": null
    },
    "9bf5faf4-32e3-437e-8080-c38eae10cfa6": {
        "chain": "Sonic",
        "project": "aave-v3",
        "symbol": "USDC",
        "tvlUsd": 484041,
        "apyBase": 4.69139,
        "apyReward": null,
        "apy": 4.69139,
        "rewardTokens": null,
        "pool": "9bf5faf4-32e3-437e-8080-c38eae10cfa6",
        "apyPct1D": 0.2436,
        "apyPct7D": -0.32636,
        "apyPct30D": 1.54817,
        "stablecoin": true,
        "ilRisk": "no",
        "exposure": "single",
        "predictions": {
            "predictedClass": "Down",
            "predictedProbability": 70,
            "binnedConfidence": 2
        },
        "poolMeta": null,
        "mu": 1.81519,
        "sigma": 0.0874,
        "count": 464,
        "outlier": false,
        "underlyingTokens": [
            "0x29219dd400f2Bf60E5a23d13Be72B486D4038894"
        ],
        "il7d": null,
        "apyBase7d": null,
        "apyMean30d": 6.16545,
        "volumeUsd1d": null,
        "volumeUsd7d": null,
        "apyBaseInception": null
    },
    "49f6e9fc-5be9-42cd-acfc-08c7404c251a": {
        "chain": "MegaETH",
        "project": "aave-v3",
        "symbol": "USDT0",
        "tvlUsd": 260748,
        "apyBase": 0.70737,
        "apyReward": null,
        "apy": 0.70737,
        "rewardTokens": null,
        "pool": "49f6e9fc-5be9-42cd-acfc-08c7404c251a",
        "apyPct1D": null,
        "apyPct7D": 0.25976,
        "apyPct30D": -1.52041,
        "stablecoin": true,
        "ilRisk": "no",
        "exposure": "single",
        "predictions": {
            "predictedClass": "Stable/Up",
            "predictedProbability": 57.99999999999999,
            "binnedConfidence": 1
        },
        "poolMeta": null,
        "mu": 1.83821,
        "sigma": 0.13247,
        "count": 78,
        "outlier": false,
        "underlyingTokens": [
            "0xB8CE59FC3717ada4C02eaDF9682A9e934F625ebb"
        ],
        "il7d": null,
        "apyBase7d": null,
        "apyMean30d": 2.73165,
        "volumeUsd1d": null,
        "volumeUsd7d": null,
        "apyBaseInception": null
    },
    "ef3c9b8f-ff81-483b-a672-21356dddaa1d": {
        "chain": "Aptos",
        "project": "aave-v3",
        "symbol": "USDC",
        "tvlUsd": 171897,
        "apyBase": 0.47052,
        "apyReward": null,
        "apy": 0.47052,
        "rewardTokens": null,
        "pool": "ef3c9b8f-ff81-483b-a672-21356dddaa1d",
        "apyPct1D": -0.01283,
        "apyPct7D": 0.0969,
        "apyPct30D": 0.07662,
        "stablecoin": true,
        "ilRisk": "no",
        "exposure": "single",
        "predictions": {
            "predictedClass": "Down",
            "predictedProbability": 51,
            "binnedConfidence": 1
        },
        "poolMeta": null,
        "mu": 0.95469,
        "sigma": 0.04432,
        "count": 91,
        "outlier": false,
        "underlyingTokens": [
            "0xbae207659db88bea0cbead6da0ed00aac12edcdda169e591cd41c94180b46f3b"
        ],
        "il7d": null,
        "apyBase7d": null,
        "apyMean30d": 0.49876,
        "volumeUsd1d": null,
        "volumeUsd7d": null,
        "apyBaseInception": null
    },
    "5a49dee1-344d-4b50-a167-8f5faab08752": {
        "chain": "Linea",
        "project": "aave-v3",
        "symbol": "USDC",
        "tvlUsd": 155649,
        "apyBase": 5.30613,
        "apyReward": null,
        "apy": 5.30613,
        "rewardTokens": null,
        "pool": "5a49dee1-344d-4b50-a167-8f5faab08752",
        "apyPct1D": -2.58732,
        "apyPct7D": 2.24934,
        "apyPct30D": 0.73317,
        "stablecoin": true,
        "ilRisk": "no",
        "exposure": "single",
        "predictions": {
            "predictedClass": "Down",
            "predictedProbability": 65,
            "binnedConfidence": 2
        },
        "poolMeta": null,
        "mu": 3.17758,
        "sigma": 0.08859,
        "count": 464,
        "outlier": false,
        "underlyingTokens": [
            "0x176211869cA2b568f2A7D4EE941E073a821EE1ff"
        ],
        "il7d": null,
        "apyBase7d": null,
        "apyMean30d": 4.98621,
        "volumeUsd1d": null,
        "volumeUsd7d": null,
        "apyBaseInception": null
    },
    "7aab7b0f-01c1-4467-bc0d-77826d870f19": {
        "chain": "Arbitrum",
        "project": "aave-v3",
        "symbol": "USDC",
        "tvlUsd": 152986,
        "apyBase": 4.10205,
        "apyReward": null,
        "apy": 4.10205,
        "rewardTokens": null,
        "pool": "7aab7b0f-01c1-4467-bc0d-77826d870f19",
        "apyPct1D": 0.00025,
        "apyPct7D": -0.09249,
        "apyPct30D": 0.55489,
        "stablecoin": true,
        "ilRisk": "no",
        "exposure": "single",
        "predictions": {
            "predictedClass": "Down",
            "predictedProbability": 62,
            "binnedConfidence": 2
        },
        "poolMeta": null,
        "mu": 3.6736,
        "sigma": 0.16096,
        "count": 1402,
        "outlier": false,
        "underlyingTokens": [
            "0xFF970A61A04b1cA14834A43f5dE4533eBDDB5CC8"
        ],
        "il7d": null,
        "apyBase7d": null,
        "apyMean30d": 4.03635,
        "volumeUsd1d": null,
        "volumeUsd7d": null,
        "apyBaseInception": null
    },
    "8d4d3acb-e1bf-471a-8256-36b90a8f4d25": {
        "chain": "Arbitrum",
        "project": "aave-v3",
        "symbol": "FRAX",
        "tvlUsd": 120951,
        "apyBase": 0.42139,
        "apyReward": null,
        "apy": 0.42139,
        "rewardTokens": null,
        "pool": "8d4d3acb-e1bf-471a-8256-36b90a8f4d25",
        "apyPct1D": 0,
        "apyPct7D": 0.0027,
        "apyPct30D": -0.15166,
        "stablecoin": true,
        "ilRisk": "no",
        "exposure": "single",
        "predictions": {
            "predictedClass": "Stable/Up",
            "predictedProbability": 71,
            "binnedConfidence": 2
        },
        "poolMeta": null,
        "mu": 4.47611,
        "sigma": 0.20946,
        "count": 962,
        "outlier": false,
        "underlyingTokens": [
            "0x17FC002b466eEc40DaE837Fc4bE5c67993ddBd6F"
        ],
        "il7d": null,
        "apyBase7d": null,
        "apyMean30d": 0.50645,
        "volumeUsd1d": null,
        "volumeUsd7d": null,
        "apyBaseInception": null
    },
    "5aabda74-2635-4870-89ab-d45b67d934d7": {
        "chain": "Ethereum",
        "project": "aave-v4",
        "symbol": "USDT",
        "tvlUsd": 120723,
        "apyBase": 5.82333,
        "apyReward": null,
        "apy": 5.82333,
        "rewardTokens": null,
        "pool": "5aabda74-2635-4870-89ab-d45b67d934d7",
        "apyPct1D": 2.57279,
        "apyPct7D": 4.67564,
        "apyPct30D": 3.16763,
        "stablecoin": true,
        "ilRisk": "no",
        "exposure": "single",
        "predictions": {
            "predictedClass": "Down",
            "predictedProbability": 84,
            "binnedConfidence": 3
        },
        "poolMeta": "Prime",
        "mu": 2.15866,
        "sigma": 0.07746,
        "count": 79,
        "outlier": false,
        "underlyingTokens": [
            "0xdAC17F958D2ee523a2206206994597C13D831ec7"
        ],
        "il7d": null,
        "apyBase7d": null,
        "apyMean30d": 1.89831,
        "volumeUsd1d": null,
        "volumeUsd7d": null,
        "apyBaseInception": null
    },
    "38f1474f-bb56-46ff-b2c6-bc07539a1f2b": {
        "chain": "Ethereum",
        "project": "aave-v4",
        "symbol": "USDC",
        "tvlUsd": 113218,
        "apyBase": 5.68862,
        "apyReward": null,
        "apy": 5.68862,
        "rewardTokens": null,
        "pool": "38f1474f-bb56-46ff-b2c6-bc07539a1f2b",
        "apyPct1D": -1.06017,
        "apyPct7D": 3.08973,
        "apyPct30D": 3.05255,
        "stablecoin": true,
        "ilRisk": "no",
        "exposure": "single",
        "predictions": {
            "predictedClass": "Down",
            "predictedProbability": 75,
            "binnedConfidence": 3
        },
        "poolMeta": "Prime",
        "mu": 2.35909,
        "sigma": 0.06579,
        "count": 79,
        "outlier": false,
        "underlyingTokens": [
            "0xA0b86991c6218b36c1d19D4a2e9Eb0cE3606eB48"
        ],
        "il7d": null,
        "apyBase7d": null,
        "apyMean30d": 2.6619,
        "volumeUsd1d": null,
        "volumeUsd7d": null,
        "apyBaseInception": null
    },
    "363e5586-cfee-402c-9b0b-be70366052e8": {
        "chain": "OP Mainnet",
        "project": "aave-v3",
        "symbol": "DAI",
        "tvlUsd": 101368,
        "apyBase": 2.90723,
        "apyReward": null,
        "apy": 2.90723,
        "rewardTokens": null,
        "pool": "363e5586-cfee-402c-9b0b-be70366052e8",
        "apyPct1D": 0.00069,
        "apyPct7D": 0.08776,
        "apyPct30D": 0.26913,
        "stablecoin": true,
        "ilRisk": "no",
        "exposure": "single",
        "predictions": {
            "predictedClass": "Down",
            "predictedProbability": 57.99999999999999,
            "binnedConfidence": 1
        },
        "poolMeta": null,
        "mu": 4.02622,
        "sigma": 0.1706,
        "count": 1402,
        "outlier": false,
        "underlyingTokens": [
            "0xDA10009cBd5D07dd0CeCc66161FC93D7c9000da1"
        ],
        "il7d": null,
        "apyBase7d": null,
        "apyMean30d": 2.90704,
        "volumeUsd1d": null,
        "volumeUsd7d": null,
        "apyBaseInception": null
    },
    "a214e900-2bcd-431f-9744-632fa5436fee": {
        "chain": "Ethereum",
        "project": "aave-v3",
        "symbol": "SDAI",
        "tvlUsd": 50384,
        "apyBase": 0,
        "apyReward": null,
        "apy": 0,
        "rewardTokens": null,
        "pool": "a214e900-2bcd-431f-9744-632fa5436fee",
        "apyPct1D": 0,
        "apyPct7D": 0,
        "apyPct30D": 0,
        "stablecoin": true,
        "ilRisk": "no",
        "exposure": "single",
        "predictions": {
            "predictedClass": null,
            "predictedProbability": null,
            "binnedConfidence": null
        },
        "poolMeta": null,
        "mu": 0,
        "sigma": 0,
        "count": 1022,
        "outlier": false,
        "underlyingTokens": [
            "0x83F20F44975D03b1b09e64809B757c47f942BEeA"
        ],
        "il7d": null,
        "apyBase7d": null,
        "apyMean30d": 0,
        "volumeUsd1d": null,
        "volumeUsd7d": null,
        "apyBaseInception": null
    },
    "bb652447-0b50-4dff-9375-30e7e826db68": {
        "chain": "Ethereum",
        "project": "aave-v4",
        "symbol": "USDC",
        "tvlUsd": 49472,
        "apyBase": 0.00045,
        "apyReward": null,
        "apy": 0.00045,
        "rewardTokens": null,
        "pool": "bb652447-0b50-4dff-9375-30e7e826db68",
        "apyPct1D": 0,
        "apyPct7D": -0.22255,
        "apyPct30D": 0,
        "stablecoin": true,
        "ilRisk": "no",
        "exposure": "single",
        "predictions": {
            "predictedClass": "Stable/Up",
            "predictedProbability": 59,
            "binnedConfidence": 1
        },
        "poolMeta": "Plus",
        "mu": 0.09221,
        "sigma": 0.0085,
        "count": 79,
        "outlier": false,
        "underlyingTokens": [
            "0xA0b86991c6218b36c1d19D4a2e9Eb0cE3606eB48"
        ],
        "il7d": null,
        "apyBase7d": null,
        "apyMean30d": 0.15756,
        "volumeUsd1d": null,
        "volumeUsd7d": null,
        "apyBaseInception": null
    },
    "72fdbf75-d830-4f18-83bf-dd7634f7a3f2": {
        "chain": "Ethereum",
        "project": "aave-v4",
        "symbol": "USDT",
        "tvlUsd": 39970,
        "apyBase": 0.16636,
        "apyReward": null,
        "apy": 0.16636,
        "rewardTokens": null,
        "pool": "72fdbf75-d830-4f18-83bf-dd7634f7a3f2",
        "apyPct1D": 1e-05,
        "apyPct7D": 5e-05,
        "apyPct30D": 0.00022,
        "stablecoin": true,
        "ilRisk": "no",
        "exposure": "single",
        "predictions": {
            "predictedClass": "Stable/Up",
            "predictedProbability": 53,
            "binnedConfidence": 1
        },
        "poolMeta": "Plus",
        "mu": 0.11848,
        "sigma": 0.00366,
        "count": 79,
        "outlier": false,
        "underlyingTokens": [
            "0xdAC17F958D2ee523a2206206994597C13D831ec7"
        ],
        "il7d": null,
        "apyBase7d": null,
        "apyMean30d": 0.16625,
        "volumeUsd1d": null,
        "volumeUsd7d": null,
        "apyBaseInception": null
    },
    "78c4b5eb-6e36-4c3a-94b5-779e37dbf9a4": {
        "chain": "Celo",
        "project": "aave-v3",
        "symbol": "USDC",
        "tvlUsd": 35152,
        "apyBase": 2.56387,
        "apyReward": null,
        "apy": 2.56387,
        "rewardTokens": null,
        "pool": "78c4b5eb-6e36-4c3a-94b5-779e37dbf9a4",
        "apyPct1D": 0.00019,
        "apyPct7D": -0.03138,
        "apyPct30D": 1.3311,
        "stablecoin": true,
        "ilRisk": "no",
        "exposure": "single",
        "predictions": {
            "predictedClass": "Stable/Up",
            "predictedProbability": 60,
            "binnedConfidence": 1
        },
        "poolMeta": null,
        "mu": 2.48075,
        "sigma": 0.11836,
        "count": 295,
        "outlier": false,
        "underlyingTokens": [
            "0xcebA9300f2b948710d2653dD7B07f33A8B32118C"
        ],
        "il7d": null,
        "apyBase7d": null,
        "apyMean30d": 2.66772,
        "volumeUsd1d": null,
        "volumeUsd7d": null,
        "apyBaseInception": null
    },
    "6817bab0-5389-40a0-84d1-78830c1d81aa": {
        "chain": "Linea",
        "project": "aave-v3",
        "symbol": "USDT",
        "tvlUsd": 21865,
        "apyBase": 8.86207,
        "apyReward": null,
        "apy": 8.86207,
        "rewardTokens": null,
        "pool": "6817bab0-5389-40a0-84d1-78830c1d81aa",
        "apyPct1D": -1.60841,
        "apyPct7D": 5.83417,
        "apyPct30D": 5.02166,
        "stablecoin": true,
        "ilRisk": "no",
        "exposure": "single",
        "predictions": {
            "predictedClass": "Down",
            "predictedProbability": 83,
            "binnedConfidence": 3
        },
        "poolMeta": null,
        "mu": 3.07473,
        "sigma": 0.09285,
        "count": 462,
        "outlier": false,
        "underlyingTokens": [
            "0xA219439258ca9da29E9Cc4cE5596924745e12B93"
        ],
        "il7d": null,
        "apyBase7d": null,
        "apyMean30d": 3.59792,
        "volumeUsd1d": null,
        "volumeUsd7d": null,
        "apyBaseInception": null
    },
    "4ef4eb9a-e22e-4190-b8f3-8c75373ad0d6": {
        "chain": "Ethereum",
        "project": "aave-v3",
        "symbol": "FRAX",
        "tvlUsd": 10460,
        "apyBase": 2.60859,
        "apyReward": null,
        "apy": 2.60859,
        "rewardTokens": null,
        "pool": "4ef4eb9a-e22e-4190-b8f3-8c75373ad0d6",
        "apyPct1D": 0,
        "apyPct7D": 0,
        "apyPct30D": null,
        "stablecoin": true,
        "ilRisk": "no",
        "exposure": "single",
        "predictions": {
            "predictedClass": "Down",
            "predictedProbability": 51,
            "binnedConfidence": 1
        },
        "poolMeta": null,
        "mu": 5.3794,
        "sigma": 0.30717,
        "count": 1021,
        "outlier": false,
        "underlyingTokens": [
            "0x853d955aCEf822Db058eb8505911ED77F175b99e"
        ],
        "il7d": null,
        "apyBase7d": null,
        "apyMean30d": 21.55417,
        "volumeUsd1d": null,
        "volumeUsd7d": null,
        "apyBaseInception": null
    }
}