{
    "7e382157-b1bc-406d-b17b-facba43b716e": {
        "chain": "Ethereum",
        "project": "aave-v3",
        "symbol": "WBTC",
        "tvlUsd": 2046254604,
        "apyBase": 0.00614,
        "apyReward": null,
        "apy": 0.00614,
        "rewardTokens": null,
        "pool": "7e382157-b1bc-406d-b17b-facba43b716e",
        "apyPct1D": 2e-05,
        "apyPct7D": -0.00051,
        "apyPct30D": 0.00077,
        "stablecoin": false,
        "ilRisk": "no",
        "exposure": "single",
        "predictions": {
            "predictedClass": "Stable/Up",
            "predictedProbability": 80,
            "binnedConfidence": 3
        },
        "poolMeta": null,
        "mu": 0.06831,
        "sigma": 0.00579,
        "count": 1251,
        "outlier": false,
        "underlyingTokens": [
            "0x2260FAC5E5542a773Aa44fBCfeDf7C193bc2C599"
        ],
        "il7d": null,
        "apyBase7d": null,
        "apyMean30d": 0.00591,
        "volumeUsd1d": null,
        "volumeUsd7d": null,
        "apyBaseInception": null
    },
    "f981a304-bb6c-45b8-b0c5-fd2f515ad23a": {
        "chain": "Ethereum",
        "project": "aave-v3",
        "symbol": "USDT",
        "tvlUsd": 561786420,
        "apyBase": 2.51736,
        "apyReward": null,
        "apy": 2.51736,
        "rewardTokens": null,
        "pool": "f981a304-bb6c-45b8-b0c5-fd2f515ad23a",
        "apyPct1D": -0.00438,
        "apyPct7D": -0.48272,
        "apyPct30D": 0.02952,
        "stablecoin": true,
        "ilRisk": "no",
        "exposure": "single",
        "predictions": {
            "predictedClass": "Stable/Up",
            "predictedProbability": 76,
            "binnedConfidence": 3
        },
        "poolMeta": null,
        "mu": 4.45405,
        "sigma": 0.17045,
        "count": 1241,
        "outlier": false,
        "underlyingTokens": [
            "0xdAC17F958D2ee523a2206206994597C13D831ec7"
        ],
        "il7d": null,
        "apyBase7d": null,
        "apyMean30d": 2.42009,
        "volumeUsd1d": null,
        "volumeUsd7d": null,
        "apyBaseInception": null
    },
    "569ab5a6-76e4-46a6-abb6-b12be4197e31": {
        "chain": "Plasma",
        "project": "aave-v3",
        "symbol": "SYRUPUSDT",
        "tvlUsd": 243703587,
        "apyBase": 0,
        "apyReward": null,
        "apy": 0,
        "rewardTokens": null,
        "pool": "569ab5a6-76e4-46a6-abb6-b12be4197e31",
        "apyPct1D": 0,
        "apyPct7D": 0,
        "apyPct30D": 0,
        "stablecoin": true,
        "ilRisk": "no",
        "exposure": "single",
        "predictions": {
            "predictedClass": null,
            "predictedProbability": null,
            "binnedConfidence": null
        },
        "poolMeta": null,
        "mu": 0,
        "sigma": 0,
        "count": 264,
        "outlier": false,
        "underlyingTokens": [
            "0xC4374775489CB9C56003BF2C9b12495fC64F0771"
        ],
        "il7d": null,
        "apyBase7d": null,
        "apyMean30d": 0,
        "volumeUsd1d": null,
        "volumeUsd7d": null,
        "apyBaseInception": null
    },
    "aa70268e-4b52-42bf-a116-608b370f9501": {
        "chain": "Ethereum",
        "project": "aave-v3",
        "symbol": "USDC",
        "tvlUsd": 181939894,
        "apyBase": 3.27105,
        "apyReward": null,
        "apy": 3.27105,
        "rewardTokens": null,
        "pool": "aa70268e-4b52-42bf-a116-608b370f9501",
        "apyPct1D": 0.02463,
        "apyPct7D": 0.24809,
        "apyPct30D": 0.14739,
        "stablecoin": true,
        "ilRisk": "no",
        "exposure": "single",
        "predictions": {
            "predictedClass": "Down",
            "predictedProbability": 60,
            "binnedConfidence": 1
        },
        "poolMeta": null,
        "mu": 4.74458,
        "sigma": 0.15788,
        "count": 1251,
        "outlier": false,
        "underlyingTokens": [
            "0xA0b86991c6218b36c1d19D4a2e9Eb0cE3606eB48"
        ],
        "il7d": null,
        "apyBase7d": null,
        "apyMean30d": 3.55617,
        "volumeUsd1d": null,
        "volumeUsd7d": null,
        "apyBaseInception": null
    },
    "7c5e69a4-2430-4fa2-b7cb-857f79d7d1bf": {
        "chain": "Arbitrum",
        "project": "aave-v3",
        "symbol": "WBTC",
        "tvlUsd": 166264982,
        "apyBase": 0.05414,
        "apyReward": null,
        "apy": 0.05414,
        "rewardTokens": null,
        "pool": "7c5e69a4-2430-4fa2-b7cb-857f79d7d1bf",
        "apyPct1D": 0.00026,
        "apyPct7D": 0.0013,
        "apyPct30D": 0.01107,
        "stablecoin": false,
        "ilRisk": "no",
        "exposure": "single",
        "predictions": {
            "predictedClass": "Stable/Up",
            "predictedProbability": 83,
            "binnedConfidence": 3
        },
        "poolMeta": null,
        "mu": 0.13465,
        "sigma": 0.01183,
        "count": 1434,
        "outlier": false,
        "underlyingTokens": [
            "0x2f2a2543B76A4166549F7aaB2e75Bef0aefC5B0f"
        ],
        "il7d": null,
        "apyBase7d": null,
        "apyMean30d": 0.05334,
        "volumeUsd1d": null,
        "volumeUsd7d": null,
        "apyBaseInception": null
    },
    "9829fc1f-8f3a-5b29-a4b1-843b2996c95d": {
        "chain": "Monad",
        "project": "aave-v3",
        "symbol": "SYRUPUSDC",
        "tvlUsd": 101803361,
        "apyBase": 0,
        "apyReward": null,
        "apy": 0,
        "rewardTokens": null,
        "pool": "9829fc1f-8f3a-5b29-a4b1-843b2996c95d",
        "apyPct1D": 0,
        "apyPct7D": 0,
        "apyPct30D": null,
        "stablecoin": true,
        "ilRisk": "no",
        "exposure": "single",
        "predictions": {
            "predictedClass": null,
            "predictedProbability": null,
            "binnedConfidence": null
        },
        "poolMeta": null,
        "mu": 0,
        "sigma": 0,
        "count": 13,
        "outlier": false,
        "underlyingTokens": [
            "0xaB6e5a0C3799d020c790D34F7B2C02639e238AF7"
        ],
        "il7d": null,
        "apyBase7d": null,
        "apyMean30d": 0,
        "volumeUsd1d": null,
        "volumeUsd7d": null,
        "apyBaseInception": null
    },
    "4dfb0ee0-6fa3-4b8b-83f7-b92e83f5242f": {
        "chain": "Mantle",
        "project": "aave-v3",
        "symbol": "SYRUPUSDT",
        "tvlUsd": 90702316,
        "apyBase": 0,
        "apyReward": null,
        "apy": 0,
        "rewardTokens": null,
        "pool": "4dfb0ee0-6fa3-4b8b-83f7-b92e83f5242f",
        "apyPct1D": 0,
        "apyPct7D": 0,
        "apyPct30D": 0,
        "stablecoin": true,
        "ilRisk": "no",
        "exposure": "single",
        "predictions": {
            "predictedClass": null,
            "predictedProbability": null,
            "binnedConfidence": null
        },
        "poolMeta": null,
        "mu": 0,
        "sigma": 0,
        "count": 105,
        "outlier": false,
        "underlyingTokens": [
            "0x051665f2455116e929b9972c36d23070F5054Ce0"
        ],
        "il7d": null,
        "apyBase7d": null,
        "apyMean30d": 0,
        "volumeUsd1d": null,
        "volumeUsd7d": null,
        "apyBaseInception": null
    },
    "a90d554a-b548-4f50-b03e-9dcb724b7777": {
        "chain": "Ethereum",
        "project": "aave-v3",
        "symbol": "USDT",
        "tvlUsd": 80080478,
        "apyBase": 2.51736,
        "apyReward": 4.27,
        "apy": 6.78736,
        "rewardTokens": [
            "0x23878914EFE38d27C4D67Ab83ed1b93A74D4086a"
        ],
        "pool": "a90d554a-b548-4f50-b03e-9dcb724b7777",
        "apyPct1D": -0.00438,
        "apyPct7D": -0.53272,
        "apyPct30D": 0.07952,
        "stablecoin": true,
        "ilRisk": "no",
        "exposure": "single",
        "predictions": {
            "predictedClass": "Down",
            "predictedProbability": 59,
            "binnedConfidence": 1
        },
        "poolMeta": "Umbrella",
        "mu": 6.66152,
        "sigma": 0.03163,
        "count": 59,
        "outlier": false,
        "underlyingTokens": [
            "0x7Bc3485026Ac48b6cf9BaF0A377477Fff5703Af8"
        ],
        "il7d": null,
        "apyBase7d": null,
        "apyMean30d": 6.65055,
        "volumeUsd1d": null,
        "volumeUsd7d": null,
        "apyBaseInception": null
    },
    "6f00d46b-8735-49ae-9ced-2a0fccc56ad0": {
        "chain": "Ethereum",
        "project": "aave-v3",
        "symbol": "USDC",
        "tvlUsd": 64263932,
        "apyBase": 3.27105,
        "apyReward": 3.6,
        "apy": 6.87105,
        "rewardTokens": [
            "0x98C23E9d8f34FEFb1B7BD6a91B7FF122F4e16F5c"
        ],
        "pool": "6f00d46b-8735-49ae-9ced-2a0fccc56ad0",
        "apyPct1D": 0.02463,
        "apyPct7D": 0.19809,
        "apyPct30D": -0.34261,
        "stablecoin": true,
        "ilRisk": "no",
        "exposure": "single",
        "predictions": {
            "predictedClass": "Stable/Up",
            "predictedProbability": 67,
            "binnedConfidence": 2
        },
        "poolMeta": "Umbrella",
        "mu": 7.2512,
        "sigma": 0.04157,
        "count": 59,
        "outlier": false,
        "underlyingTokens": [
            "0xD4fa2D31b7968E448877f69A96DE69f5de8cD23E"
        ],
        "il7d": null,
        "apyBase7d": null,
        "apyMean30d": 7.28358,
        "volumeUsd1d": null,
        "volumeUsd7d": null,
        "apyBaseInception": null
    },
    "8bba1554-1318-54ad-9143-0972406e9428": {
        "chain": "Monad",
        "project": "aave-v3",
        "symbol": "USDT0",
        "tvlUsd": 59838809,
        "apyBase": 0.6339,
        "apyReward": 6,
        "apy": 6.6339,
        "rewardTokens": [
            "0x561Ad6156D0106E7a59EE788759dF7B7Ec679BD0"
        ],
        "pool": "8bba1554-1318-54ad-9143-0972406e9428",
        "apyPct1D": -0.04785,
        "apyPct7D": -0.4885,
        "apyPct30D": null,
        "stablecoin": true,
        "ilRisk": "no",
        "exposure": "single",
        "predictions": {
            "predictedClass": "Stable/Up",
            "predictedProbability": 70,
            "binnedConfidence": 2
        },
        "poolMeta": null,
        "mu": 7.50523,
        "sigma": 0.045,
        "count": 13,
        "outlier": false,
        "underlyingTokens": [
            "0xe7cd86e13AC4309349F30B3435a9d337750fC82D"
        ],
        "il7d": null,
        "apyBase7d": null,
        "apyMean30d": 7.7143,
        "volumeUsd1d": null,
        "volumeUsd7d": null,
        "apyBaseInception": null
    },
    "58d18059-f1d1-45ed-acd3-f386e98cc506": {
        "chain": "Polygon",
        "project": "aave-v3",
        "symbol": "WBTC",
        "tvlUsd": 51097782,
        "apyBase": 0.01901,
        "apyReward": null,
        "apy": 0.01901,
        "rewardTokens": null,
        "pool": "58d18059-f1d1-45ed-acd3-f386e98cc506",
        "apyPct1D": 0.00021,
        "apyPct7D": 0.00038,
        "apyPct30D": -0.00015,
        "stablecoin": false,
        "ilRisk": "no",
        "exposure": "single",
        "predictions": {
            "predictedClass": "Stable/Up",
            "predictedProbability": 72,
            "binnedConfidence": 2
        },
        "poolMeta": null,
        "mu": 0.03308,
        "sigma": 0.00842,
        "count": 1434,
        "outlier": false,
        "underlyingTokens": [
            "0x1BFD67037B42Cf73acF2047067bd4F2C47D9BfD6"
        ],
        "il7d": null,
        "apyBase7d": null,
        "apyMean30d": 0.01869,
        "volumeUsd1d": null,
        "volumeUsd7d": null,
        "apyBaseInception": null
    },
    "e338c687-a5d8-4abf-bc04-127990811b0a": {
        "chain": "Plasma",
        "project": "aave-v3",
        "symbol": "USDT0",
        "tvlUsd": 49181626,
        "apyBase": 5.17713,
        "apyReward": 0.98906,
        "apy": 6.16619,
        "rewardTokens": [
            "0x6100E367285b01F48D07953803A2d8dCA5D19873"
        ],
        "pool": "e338c687-a5d8-4abf-bc04-127990811b0a",
        "apyPct1D": 1.42639,
        "apyPct7D": 2.19008,
        "apyPct30D": 2.14396,
        "stablecoin": true,
        "ilRisk": "no",
        "exposure": "single",
        "predictions": {
            "predictedClass": "Down",
            "predictedProbability": 77,
            "binnedConfidence": 3
        },
        "poolMeta": null,
        "mu": 3.74705,
        "sigma": 0.06085,
        "count": 289,
        "outlier": false,
        "underlyingTokens": [
            "0xB8CE59FC3717ada4C02eaDF9682A9e934F625ebb"
        ],
        "il7d": null,
        "apyBase7d": null,
        "apyMean30d": 3.99705,
        "volumeUsd1d": null,
        "volumeUsd7d": null,
        "apyBaseInception": null
    },
    "f9258dd3-f50a-4ea3-8501-49b4b2603a5f": {
        "chain": "Ethereum",
        "project": "aave-v4",
        "symbol": "WBTC",
        "tvlUsd": 37538229,
        "apyBase": 0.00099,
        "apyReward": null,
        "apy": 0.00099,
        "rewardTokens": null,
        "pool": "f9258dd3-f50a-4ea3-8501-49b4b2603a5f",
        "apyPct1D": 0.00017,
        "apyPct7D": -0.00012,
        "apyPct30D": -0.00102,
        "stablecoin": false,
        "ilRisk": "no",
        "exposure": "single",
        "predictions": {
            "predictedClass": "Stable/Up",
            "predictedProbability": 79,
            "binnedConfidence": 3
        },
        "poolMeta": "Core",
        "mu": 0.00532,
        "sigma": 0.00021,
        "count": 105,
        "outlier": false,
        "underlyingTokens": [
            "0x2260FAC5E5542a773Aa44fBCfeDf7C193bc2C599"
        ],
        "il7d": null,
        "apyBase7d": null,
        "apyMean30d": 0.00202,
        "volumeUsd1d": null,
        "volumeUsd7d": null,
        "apyBaseInception": null
    },
    "7e0661bf-8cf3-45e6-9424-31916d4c7b84": {
        "chain": "Base",
        "project": "aave-v3",
        "symbol": "USDC",
        "tvlUsd": 32592981,
        "apyBase": 3.02913,
        "apyReward": null,
        "apy": 3.02913,
        "rewardTokens": null,
        "pool": "7e0661bf-8cf3-45e6-9424-31916d4c7b84",
        "apyPct1D": -0.12123,
        "apyPct7D": -0.05073,
        "apyPct30D": -0.14581,
        "stablecoin": true,
        "ilRisk": "no",
        "exposure": "single",
        "predictions": {
            "predictedClass": "Stable/Up",
            "predictedProbability": 88,
            "binnedConfidence": 3
        },
        "poolMeta": null,
        "mu": 4.86376,
        "sigma": 0.12902,
        "count": 856,
        "outlier": false,
        "underlyingTokens": [
            "0x833589fCD6eDb6E08f4c7C32D4f71b54bdA02913"
        ],
        "il7d": null,
        "apyBase7d": null,
        "apyMean30d": 3.13372,
        "volumeUsd1d": null,
        "volumeUsd7d": null,
        "apyBaseInception": null
    },
    "d9fa8e14-0447-4207-9ae8-7810199dfa1f": {
        "chain": "Arbitrum",
        "project": "aave-v3",
        "symbol": "USDC",
        "tvlUsd": 29928559,
        "apyBase": 2.68428,
        "apyReward": null,
        "apy": 2.68428,
        "rewardTokens": null,
        "pool": "d9fa8e14-0447-4207-9ae8-7810199dfa1f",
        "apyPct1D": 0.05481,
        "apyPct7D": 0.19052,
        "apyPct30D": 0.46501,
        "stablecoin": true,
        "ilRisk": "no",
        "exposure": "single",
        "predictions": {
            "predictedClass": "Stable/Up",
            "predictedProbability": 83,
            "binnedConfidence": 3
        },
        "poolMeta": null,
        "mu": 5.06251,
        "sigma": 0.16532,
        "count": 1110,
        "outlier": false,
        "underlyingTokens": [
            "0xaf88d065e77c8cC2239327C5EDb3A432268e5831"
        ],
        "il7d": null,
        "apyBase7d": null,
        "apyMean30d": 2.32756,
        "volumeUsd1d": null,
        "volumeUsd7d": null,
        "apyBaseInception": null
    },
    "47da0cdd-7b1d-4927-9545-20b53b73afa8": {
        "chain": "Mantle",
        "project": "aave-v3",
        "symbol": "USDT0",
        "tvlUsd": 27645159,
        "apyBase": 3.06959,
        "apyReward": null,
        "apy": 3.06959,
        "rewardTokens": null,
        "pool": "47da0cdd-7b1d-4927-9545-20b53b73afa8",
        "apyPct1D": -3.89999,
        "apyPct7D": -0.92522,
        "apyPct30D": -1.45397,
        "stablecoin": true,
        "ilRisk": "no",
        "exposure": "single",
        "predictions": {
            "predictedClass": "Stable/Up",
            "predictedProbability": 86,
            "binnedConfidence": 3
        },
        "poolMeta": null,
        "mu": 4.91609,
        "sigma": 0.10351,
        "count": 104,
        "outlier": false,
        "underlyingTokens": [
            "0x779Ded0c9e1022225f8E0630b35a9b54bE713736"
        ],
        "il7d": null,
        "apyBase7d": null,
        "apyMean30d": 5.99339,
        "volumeUsd1d": null,
        "volumeUsd7d": null,
        "apyBaseInception": null
    },
    "3665ee7e-6c5d-49d9-abb7-c47ab5d9d4ac": {
        "chain": "Ethereum",
        "project": "aave-v3",
        "symbol": "DAI",
        "tvlUsd": 20466026,
        "apyBase": 2.81882,
        "apyReward": null,
        "apy": 2.81882,
        "rewardTokens": null,
        "pool": "3665ee7e-6c5d-49d9-abb7-c47ab5d9d4ac",
        "apyPct1D": 0.02397,
        "apyPct7D": 0.01496,
        "apyPct30D": -0.59108,
        "stablecoin": true,
        "ilRisk": "no",
        "exposure": "single",
        "predictions": {
            "predictedClass": "Stable/Up",
            "predictedProbability": 85,
            "binnedConfidence": 3
        },
        "poolMeta": null,
        "mu": 4.44718,
        "sigma": 0.17157,
        "count": 1251,
        "outlier": false,
        "underlyingTokens": [
            "0x6B175474E89094C44Da98b954EedeAC495271d0F"
        ],
        "il7d": null,
        "apyBase7d": null,
        "apyMean30d": 3.96302,
        "volumeUsd1d": null,
        "volumeUsd7d": null,
        "apyBaseInception": null
    },
    "0a1131e6-a59d-537c-b18f-826b9583f01f": {
        "chain": "Monad",
        "project": "aave-v3",
        "symbol": "USDC",
        "tvlUsd": 16813963,
        "apyBase": 2.10247,
        "apyReward": 6,
        "apy": 8.10247,
        "rewardTokens": [
            "0x561Ad6156D0106E7a59EE788759dF7B7Ec679BD0"
        ],
        "pool": "0a1131e6-a59d-537c-b18f-826b9583f01f",
        "apyPct1D": -1.06107,
        "apyPct7D": -0.80184,
        "apyPct30D": null,
        "stablecoin": true,
        "ilRisk": "no",
        "exposure": "single",
        "predictions": {
            "predictedClass": "Stable/Up",
            "predictedProbability": 66,
            "binnedConfidence": 2
        },
        "poolMeta": null,
        "mu": 9.78884,
        "sigma": 0.11308,
        "count": 13,
        "outlier": false,
        "underlyingTokens": [
            "0x754704Bc059F8C67012fEd69BC8A327a5aafb603"
        ],
        "il7d": null,
        "apyBase7d": null,
        "apyMean30d": 10.38231,
        "volumeUsd1d": null,
        "volumeUsd7d": null,
        "apyBaseInception": null
    },
    "e053590b-54f1-40aa-ae0d-14e701ca734c": {
        "chain": "OP Mainnet",
        "project": "aave-v3",
        "symbol": "WBTC",
        "tvlUsd": 13560869,
        "apyBase": 0.01929,
        "apyReward": null,
        "apy": 0.01929,
        "rewardTokens": null,
        "pool": "e053590b-54f1-40aa-ae0d-14e701ca734c",
        "apyPct1D": 0.00037,
        "apyPct7D": -0.00311,
        "apyPct30D": -0.00454,
        "stablecoin": false,
        "ilRisk": "no",
        "exposure": "single",
        "predictions": {
            "predictedClass": "Stable/Up",
            "predictedProbability": 86,
            "binnedConfidence": 3
        },
        "poolMeta": null,
        "mu": 0.18568,
        "sigma": 0.0319,
        "count": 1434,
        "outlier": false,
        "underlyingTokens": [
            "0x68f180fcCe6836688e9084f035309E29Bf0A2095"
        ],
        "il7d": null,
        "apyBase7d": null,
        "apyMean30d": 0.0225,
        "volumeUsd1d": null,
        "volumeUsd7d": null,
        "apyBaseInception": null
    },
    "29be6a85-414f-4a66-b075-98863278912a": {
        "chain": "BSC",
        "project": "aave-v3",
        "symbol": "USDT",
        "tvlUsd": 13275187,
        "apyBase": 2.3014,
        "apyReward": null,
        "apy": 2.3014,
        "rewardTokens": null,
        "pool": "29be6a85-414f-4a66-b075-98863278912a",
        "apyPct1D": 0.02165,
        "apyPct7D": 0.01526,
        "apyPct30D": 0.47284,
        "stablecoin": true,
        "ilRisk": "no",
        "exposure": "single",
        "predictions": {
            "predictedClass": "Stable/Up",
            "predictedProbability": 93,
            "binnedConfidence": 3
        },
        "poolMeta": null,
        "mu": 3.91529,
        "sigma": 0.10829,
        "count": 764,
        "outlier": false,
        "underlyingTokens": [
            "0x55d398326f99059fF775485246999027B3197955"
        ],
        "il7d": null,
        "apyBase7d": null,
        "apyMean30d": 2.27505,
        "volumeUsd1d": null,
        "volumeUsd7d": null,
        "apyBaseInception": null
    },
    "7e7821a2-3d20-4ae7-9c3d-04cd57904555": {
        "chain": "Polygon",
        "project": "aave-v3",
        "symbol": "USDT0",
        "tvlUsd": 13186979,
        "apyBase": 2.65136,
        "apyReward": null,
        "apy": 2.65136,
        "rewardTokens": null,
        "pool": "7e7821a2-3d20-4ae7-9c3d-04cd57904555",
        "apyPct1D": 0.00023,
        "apyPct7D": 0.02287,
        "apyPct30D": -0.1717,
        "stablecoin": true,
        "ilRisk": "no",
        "exposure": "single",
        "predictions": {
            "predictedClass": "Stable/Up",
            "predictedProbability": 84,
            "binnedConfidence": 3
        },
        "poolMeta": null,
        "mu": 4.53741,
        "sigma": 0.16386,
        "count": 1429,
        "outlier": false,
        "underlyingTokens": [
            "0xc2132D05D31c914a87C6611C10748AEb04B58e8F"
        ],
        "il7d": null,
        "apyBase7d": null,
        "apyMean30d": 2.85539,
        "volumeUsd1d": null,
        "volumeUsd7d": null,
        "apyBaseInception": null
    },
    "974b8732-2dce-4a46-8204-7f9e6b7efb71": {
        "chain": "Base",
        "project": "aave-v3",
        "symbol": "SYRUPUSDC",
        "tvlUsd": 12799132,
        "apyBase": 0,
        "apyReward": null,
        "apy": 0,
        "rewardTokens": null,
        "pool": "974b8732-2dce-4a46-8204-7f9e6b7efb71",
        "apyPct1D": 0,
        "apyPct7D": 0,
        "apyPct30D": 0,
        "stablecoin": true,
        "ilRisk": "no",
        "exposure": "single",
        "predictions": {
            "predictedClass": null,
            "predictedProbability": null,
            "binnedConfidence": null
        },
        "poolMeta": null,
        "mu": 0,
        "sigma": 0,
        "count": 170,
        "outlier": false,
        "underlyingTokens": [
            "0x660975730059246A68521a3e2FBD4740173100f5"
        ],
        "il7d": null,
        "apyBase7d": null,
        "apyMean30d": 0,
        "volumeUsd1d": null,
        "volumeUsd7d": null,
        "apyBaseInception": null
    },
    "1b8b4cdb-0728-42a8-bf13-2c8fea7427ee": {
        "chain": "Polygon",
        "project": "aave-v3",
        "symbol": "USDC",
        "tvlUsd": 11930270,
        "apyBase": 2.81775,
        "apyReward": null,
        "apy": 2.81775,
        "rewardTokens": null,
        "pool": "1b8b4cdb-0728-42a8-bf13-2c8fea7427ee",
        "apyPct1D": 0.03469,
        "apyPct7D": 0.05122,
        "apyPct30D": -0.09939,
        "stablecoin": true,
        "ilRisk": "no",
        "exposure": "single",
        "predictions": {
            "predictedClass": "Stable/Up",
            "predictedProbability": 86,
            "binnedConfidence": 3
        },
        "poolMeta": null,
        "mu": 5.11056,
        "sigma": 0.1511,
        "count": 934,
        "outlier": false,
        "underlyingTokens": [
            "0x3c499c542cEF5E3811e1192ce70d8cC03d5c3359"
        ],
        "il7d": null,
        "apyBase7d": null,
        "apyMean30d": 2.79958,
        "volumeUsd1d": null,
        "volumeUsd7d": null,
        "apyBaseInception": null
    },
    "0925bef8-3d9f-4ad7-81e2-34feec9d3d29": {
        "chain": "Ethereum",
        "project": "aave-v4",
        "symbol": "WBTC",
        "tvlUsd": 9871196,
        "apyBase": 0,
        "apyReward": null,
        "apy": 0,
        "rewardTokens": null,
        "pool": "0925bef8-3d9f-4ad7-81e2-34feec9d3d29",
        "apyPct1D": 0,
        "apyPct7D": 0,
        "apyPct30D": 0,
        "stablecoin": false,
        "ilRisk": "no",
        "exposure": "single",
        "predictions": {
            "predictedClass": null,
            "predictedProbability": null,
            "binnedConfidence": null
        },
        "poolMeta": "Prime",
        "mu": 0,
        "sigma": 0,
        "count": 106,
        "outlier": false,
        "underlyingTokens": [
            "0x2260FAC5E5542a773Aa44fBCfeDf7C193bc2C599"
        ],
        "il7d": null,
        "apyBase7d": null,
        "apyMean30d": 0,
        "volumeUsd1d": null,
        "volumeUsd7d": null,
        "apyBaseInception": null
    },
    "a79fdd93-2747-43ee-bf53-0c372192964d": {
        "chain": "Ethereum",
        "project": "aave-v3",
        "symbol": "SYRUPUSDT",
        "tvlUsd": 9604163,
        "apyBase": 0,
        "apyReward": null,
        "apy": 0,
        "rewardTokens": null,
        "pool": "a79fdd93-2747-43ee-bf53-0c372192964d",
        "apyPct1D": 0,
        "apyPct7D": 0,
        "apyPct30D": 0,
        "stablecoin": true,
        "ilRisk": "no",
        "exposure": "single",
        "predictions": {
            "predictedClass": null,
            "predictedProbability": null,
            "binnedConfidence": null
        },
        "poolMeta": null,
        "mu": 0,
        "sigma": 0,
        "count": 223,
        "outlier": false,
        "underlyingTokens": [
            "0x356B8d89c1e1239Cbbb9dE4815c39A1474d5BA7D"
        ],
        "il7d": null,
        "apyBase7d": null,
        "apyMean30d": 0,
        "volumeUsd1d": null,
        "volumeUsd7d": null,
        "apyBaseInception": null
    },
    "32f04d80-25f9-439f-838d-3b15becf2d21": {
        "chain": "Gnosis",
        "project": "aave-v3",
        "symbol": "SDAI",
        "tvlUsd": 8712500,
        "apyBase": 0,
        "apyReward": null,
        "apy": 0,
        "rewardTokens": null,
        "pool": "32f04d80-25f9-439f-838d-3b15becf2d21",
        "apyPct1D": 0,
        "apyPct7D": 0,
        "apyPct30D": 0,
        "stablecoin": true,
        "ilRisk": "no",
        "exposure": "single",
        "predictions": {
            "predictedClass": null,
            "predictedProbability": null,
            "binnedConfidence": null
        },
        "poolMeta": null,
        "mu": 0,
        "sigma": 0,
        "count": 899,
        "outlier": false,
        "underlyingTokens": [
            "0xaf204776c7245bF4147c2612BF6e5972Ee483701"
        ],
        "il7d": null,
        "apyBase7d": null,
        "apyMean30d": 0,
        "volumeUsd1d": null,
        "volumeUsd7d": null,
        "apyBaseInception": null
    },
    "baee0253-eb6e-4a08-a579-a2acd4f034b2": {
        "chain": "Ethereum",
        "project": "aave-v3",
        "symbol": "USDTB",
        "tvlUsd": 5415319,
        "apyBase": 2.45834,
        "apyReward": 3.4,
        "apy": 5.85834,
        "rewardTokens": [
            "0x04EADd7B10ea9a484c60860aea7A7C0AEc09B9F0"
        ],
        "pool": "baee0253-eb6e-4a08-a579-a2acd4f034b2",
        "apyPct1D": -4.79546,
        "apyPct7D": 2.39557,
        "apyPct30D": -0.16414,
        "stablecoin": true,
        "ilRisk": "no",
        "exposure": "single",
        "predictions": {
            "predictedClass": "Down",
            "predictedProbability": 61,
            "binnedConfidence": 2
        },
        "poolMeta": null,
        "mu": 2.19853,
        "sigma": 0.09811,
        "count": 404,
        "outlier": false,
        "underlyingTokens": [
            "0xC139190F447e929f090Edeb554D95AbB8b18aC1C"
        ],
        "il7d": null,
        "apyBase7d": null,
        "apyMean30d": 6.43507,
        "volumeUsd1d": null,
        "volumeUsd7d": null,
        "apyBaseInception": null
    },
    "c4b05318-88af-4536-a834-f5fc8940d2d3": {
        "chain": "Avalanche",
        "project": "aave-v3",
        "symbol": "USDC",
        "tvlUsd": 5167406,
        "apyBase": 4.26792,
        "apyReward": null,
        "apy": 4.26792,
        "rewardTokens": null,
        "pool": "c4b05318-88af-4536-a834-f5fc8940d2d3",
        "apyPct1D": 1.03018,
        "apyPct7D": 1.07767,
        "apyPct30D": 1.1456,
        "stablecoin": true,
        "ilRisk": "no",
        "exposure": "single",
        "predictions": {
            "predictedClass": "Down",
            "predictedProbability": 53,
            "binnedConfidence": 1
        },
        "poolMeta": null,
        "mu": 4.33362,
        "sigma": 0.184,
        "count": 1276,
        "outlier": false,
        "underlyingTokens": [
            "0xB97EF9Ef8734C71904D8002F8b6Bc66Dd9c48a6E"
        ],
        "il7d": null,
        "apyBase7d": null,
        "apyMean30d": 3.29377,
        "volumeUsd1d": null,
        "volumeUsd7d": null,
        "apyBaseInception": null
    },
    "15cf7c05-b5f0-4bde-8745-a791528c4381": {
        "chain": "BSC",
        "project": "aave-v3",
        "symbol": "USDC",
        "tvlUsd": 4392590,
        "apyBase": 2.2717,
        "apyReward": null,
        "apy": 2.2717,
        "rewardTokens": null,
        "pool": "15cf7c05-b5f0-4bde-8745-a791528c4381",
        "apyPct1D": 0.04296,
        "apyPct7D": 0.13765,
        "apyPct30D": 0.37313,
        "stablecoin": true,
        "ilRisk": "no",
        "exposure": "single",
        "predictions": {
            "predictedClass": "Stable/Up",
            "predictedProbability": 91,
            "binnedConfidence": 3
        },
        "poolMeta": null,
        "mu": 4.03036,
        "sigma": 0.12161,
        "count": 764,
        "outlier": false,
        "underlyingTokens": [
            "0x8AC76a51cc950d9822D68b83fE1Ad97B32Cd580d"
        ],
        "il7d": null,
        "apyBase7d": null,
        "apyMean30d": 2.04893,
        "volumeUsd1d": null,
        "volumeUsd7d": null,
        "apyBaseInception": null
    },
    "e6692d08-85b6-4b50-952b-7c5c531862fe": {
        "chain": "Avalanche",
        "project": "aave-v3",
        "symbol": "USDT",
        "tvlUsd": 2512072,
        "apyBase": 3.66874,
        "apyReward": null,
        "apy": 3.66874,
        "rewardTokens": null,
        "pool": "e6692d08-85b6-4b50-952b-7c5c531862fe",
        "apyPct1D": -1.08666,
        "apyPct7D": -0.64535,
        "apyPct30D": -0.24608,
        "stablecoin": true,
        "ilRisk": "no",
        "exposure": "single",
        "predictions": {
            "predictedClass": "Stable/Up",
            "predictedProbability": 56.99999999999999,
            "binnedConfidence": 1
        },
        "poolMeta": null,
        "mu": 4.30607,
        "sigma": 0.17944,
        "count": 1276,
        "outlier": false,
        "underlyingTokens": [
            "0x9702230A8Ea53601f5cD2dc00fDBc13d4dF4A8c7"
        ],
        "il7d": null,
        "apyBase7d": null,
        "apyMean30d": 3.60807,
        "volumeUsd1d": null,
        "volumeUsd7d": null,
        "apyBaseInception": null
    },
    "27296bf9-617a-46e4-9d6d-eefc71e9e0b6": {
        "chain": "Ethereum",
        "project": "aave-v3",
        "symbol": "USDC",
        "tvlUsd": 2351910,
        "apyBase": 2.71588,
        "apyReward": null,
        "apy": 2.71588,
        "rewardTokens": null,
        "pool": "27296bf9-617a-46e4-9d6d-eefc71e9e0b6",
        "apyPct1D": -0.00076,
        "apyPct7D": -0.02379,
        "apyPct30D": 0.05464,
        "stablecoin": true,
        "ilRisk": "no",
        "exposure": "single",
        "predictions": {
            "predictedClass": "Down",
            "predictedProbability": 57.99999999999999,
            "binnedConfidence": 1
        },
        "poolMeta": "Aave Horizon Market",
        "mu": 2.77702,
        "sigma": 0.03082,
        "count": 166,
        "outlier": false,
        "underlyingTokens": [
            "0xA0b86991c6218b36c1d19D4a2e9Eb0cE3606eB48"
        ],
        "il7d": null,
        "apyBase7d": null,
        "apyMean30d": 2.63981,
        "volumeUsd1d": null,
        "volumeUsd7d": null,
        "apyBaseInception": null
    },
    "3e669ce8-74c5-4fc9-bf85-f40a924c6407": {
        "chain": "Avalanche",
        "project": "aave-v3",
        "symbol": "DAI.E",
        "tvlUsd": 2168931,
        "apyBase": 1.29455,
        "apyReward": null,
        "apy": 1.29455,
        "rewardTokens": null,
        "pool": "3e669ce8-74c5-4fc9-bf85-f40a924c6407",
        "apyPct1D": 0.04349,
        "apyPct7D": 0.01919,
        "apyPct30D": -1.20852,
        "stablecoin": true,
        "ilRisk": "no",
        "exposure": "single",
        "predictions": {
            "predictedClass": "Stable/Up",
            "predictedProbability": 69,
            "binnedConfidence": 2
        },
        "poolMeta": null,
        "mu": 3.29743,
        "sigma": 0.15688,
        "count": 1277,
        "outlier": false,
        "underlyingTokens": [
            "0xd586E7F844cEa2F87f50152665BCbc2C279D8d70"
        ],
        "il7d": null,
        "apyBase7d": null,
        "apyMean30d": 1.42432,
        "volumeUsd1d": null,
        "volumeUsd7d": null,
        "apyBaseInception": null
    },
    "effcb4a4-4dcb-45e5-935d-f15542c13e6b": {
        "chain": "Ethereum",
        "project": "aave-v3",
        "symbol": "USDC",
        "tvlUsd": 1786703,
        "apyBase": 2.33637,
        "apyReward": null,
        "apy": 2.33637,
        "rewardTokens": null,
        "pool": "effcb4a4-4dcb-45e5-935d-f15542c13e6b",
        "apyPct1D": 0.00193,
        "apyPct7D": 0.07269,
        "apyPct30D": 0.87281,
        "stablecoin": true,
        "ilRisk": "no",
        "exposure": "single",
        "predictions": {
            "predictedClass": "Stable/Up",
            "predictedProbability": 80,
            "binnedConfidence": 3
        },
        "poolMeta": "Prime Instance",
        "mu": 4.15893,
        "sigma": 0.12433,
        "count": 613,
        "outlier": false,
        "underlyingTokens": [
            "0xA0b86991c6218b36c1d19D4a2e9Eb0cE3606eB48"
        ],
        "il7d": null,
        "apyBase7d": null,
        "apyMean30d": 2.0839,
        "volumeUsd1d": null,
        "volumeUsd7d": null,
        "apyBaseInception": null
    },
    "32cb38a5-b9b9-441a-bf07-8fab47b999d3": {
        "chain": "Mantle",
        "project": "aave-v3",
        "symbol": "USDC",
        "tvlUsd": 1644970,
        "apyBase": 2.83726,
        "apyReward": null,
        "apy": 2.83726,
        "rewardTokens": null,
        "pool": "32cb38a5-b9b9-441a-bf07-8fab47b999d3",
        "apyPct1D": -5.04478,
        "apyPct7D": -0.28175,
        "apyPct30D": -2.80131,
        "stablecoin": true,
        "ilRisk": "no",
        "exposure": "single",
        "predictions": {
            "predictedClass": "Stable/Up",
            "predictedProbability": 78,
            "binnedConfidence": 3
        },
        "poolMeta": null,
        "mu": 5.96877,
        "sigma": 0.12253,
        "count": 104,
        "outlier": false,
        "underlyingTokens": [
            "0x09Bc4E0D864854c6aFB6eB9A9cdF58aC190D0dF9"
        ],
        "il7d": null,
        "apyBase7d": null,
        "apyMean30d": 7.16842,
        "volumeUsd1d": null,
        "volumeUsd7d": null,
        "apyBaseInception": null
    },
    "72fdbf75-d830-4f18-83bf-dd7634f7a3f2": {
        "chain": "Ethereum",
        "project": "aave-v4",
        "symbol": "USDT",
        "tvlUsd": 1451584,
        "apyBase": 1.07029,
        "apyReward": null,
        "apy": 1.07029,
        "rewardTokens": null,
        "pool": "72fdbf75-d830-4f18-83bf-dd7634f7a3f2",
        "apyPct1D": -0.01329,
        "apyPct7D": -0.17571,
        "apyPct30D": 0.90395,
        "stablecoin": true,
        "ilRisk": "no",
        "exposure": "single",
        "predictions": {
            "predictedClass": "Stable/Up",
            "predictedProbability": 61,
            "binnedConfidence": 2
        },
        "poolMeta": "Plus",
        "mu": 0.26635,
        "sigma": 0.0181,
        "count": 106,
        "outlier": false,
        "underlyingTokens": [
            "0xdAC17F958D2ee523a2206206994597C13D831ec7"
        ],
        "il7d": null,
        "apyBase7d": null,
        "apyMean30d": 0.63098,
        "volumeUsd1d": null,
        "volumeUsd7d": null,
        "apyBaseInception": null
    },
    "bb652447-0b50-4dff-9375-30e7e826db68": {
        "chain": "Ethereum",
        "project": "aave-v4",
        "symbol": "USDC",
        "tvlUsd": 1418278,
        "apyBase": 1.12014,
        "apyReward": null,
        "apy": 1.12014,
        "rewardTokens": null,
        "pool": "bb652447-0b50-4dff-9375-30e7e826db68",
        "apyPct1D": 8e-05,
        "apyPct7D": -0.75713,
        "apyPct30D": 0.8971,
        "stablecoin": true,
        "ilRisk": "no",
        "exposure": "single",
        "predictions": {
            "predictedClass": "Down",
            "predictedProbability": 56.00000000000001,
            "binnedConfidence": 1
        },
        "poolMeta": "Plus",
        "mu": 0.30724,
        "sigma": 0.02921,
        "count": 106,
        "outlier": false,
        "underlyingTokens": [
            "0xA0b86991c6218b36c1d19D4a2e9Eb0cE3606eB48"
        ],
        "il7d": null,
        "apyBase7d": null,
        "apyMean30d": 0.84965,
        "volumeUsd1d": null,
        "volumeUsd7d": null,
        "apyBaseInception": null
    },
    "9bf5faf4-32e3-437e-8080-c38eae10cfa6": {
        "chain": "Sonic",
        "project": "aave-v3",
        "symbol": "USDC",
        "tvlUsd": 1276030,
        "apyBase": 1.91251,
        "apyReward": null,
        "apy": 1.91251,
        "rewardTokens": null,
        "pool": "9bf5faf4-32e3-437e-8080-c38eae10cfa6",
        "apyPct1D": 0.00137,
        "apyPct7D": 0.06266,
        "apyPct30D": -2.21605,
        "stablecoin": true,
        "ilRisk": "no",
        "exposure": "single",
        "predictions": {
            "predictedClass": "Stable/Up",
            "predictedProbability": 67,
            "binnedConfidence": 2
        },
        "poolMeta": null,
        "mu": 1.83651,
        "sigma": 0.08583,
        "count": 491,
        "outlier": false,
        "underlyingTokens": [
            "0x29219dd400f2Bf60E5a23d13Be72B486D4038894"
        ],
        "il7d": null,
        "apyBase7d": null,
        "apyMean30d": 2.48282,
        "volumeUsd1d": null,
        "volumeUsd7d": null,
        "apyBaseInception": null
    },
    "0758c3b8-4ffb-4176-b0a9-f446e367db46": {
        "chain": "OP Mainnet",
        "project": "aave-v3",
        "symbol": "USDC",
        "tvlUsd": 1206710,
        "apyBase": 3.21683,
        "apyReward": null,
        "apy": 3.21683,
        "rewardTokens": null,
        "pool": "0758c3b8-4ffb-4176-b0a9-f446e367db46",
        "apyPct1D": -0.81797,
        "apyPct7D": 0.40205,
        "apyPct30D": 0.73637,
        "stablecoin": true,
        "ilRisk": "no",
        "exposure": "single",
        "predictions": {
            "predictedClass": "Stable/Up",
            "predictedProbability": 82,
            "binnedConfidence": 3
        },
        "poolMeta": null,
        "mu": 5.301,
        "sigma": 0.18504,
        "count": 957,
        "outlier": false,
        "underlyingTokens": [
            "0x0b2C639c533813f4Aa9D7837CAf62653d097Ff85"
        ],
        "il7d": null,
        "apyBase7d": null,
        "apyMean30d": 3.00746,
        "volumeUsd1d": null,
        "volumeUsd7d": null,
        "apyBaseInception": null
    },
    "461505e0-e631-4af0-b0e9-6a861d917939": {
        "chain": "Gnosis",
        "project": "aave-v3",
        "symbol": "USDC.E",
        "tvlUsd": 1158201,
        "apyBase": 2.48943,
        "apyReward": null,
        "apy": 2.48943,
        "rewardTokens": null,
        "pool": "461505e0-e631-4af0-b0e9-6a861d917939",
        "apyPct1D": -0.00043,
        "apyPct7D": 0.05541,
        "apyPct30D": 0.02544,
        "stablecoin": true,
        "ilRisk": "no",
        "exposure": "single",
        "predictions": {
            "predictedClass": "Stable/Up",
            "predictedProbability": 51,
            "binnedConfidence": 1
        },
        "poolMeta": null,
        "mu": 2.6185,
        "sigma": 0.04463,
        "count": 705,
        "outlier": false,
        "underlyingTokens": [
            "0x2a22f9c3b484c3629090FeED35F17Ff8F88f76F0"
        ],
        "il7d": null,
        "apyBase7d": null,
        "apyMean30d": 2.52642,
        "volumeUsd1d": null,
        "volumeUsd7d": null,
        "apyBaseInception": null
    },
    "a8e3d841-2788-4647-ad54-5a36fac451b1": {
        "chain": "Arbitrum",
        "project": "aave-v3",
        "symbol": "DAI",
        "tvlUsd": 1108774,
        "apyBase": 1.98281,
        "apyReward": null,
        "apy": 1.98281,
        "rewardTokens": null,
        "pool": "a8e3d841-2788-4647-ad54-5a36fac451b1",
        "apyPct1D": 0.01034,
        "apyPct7D": 0.15738,
        "apyPct30D": 0.25454,
        "stablecoin": true,
        "ilRisk": "no",
        "exposure": "single",
        "predictions": {
            "predictedClass": "Stable/Up",
            "predictedProbability": 85,
            "binnedConfidence": 3
        },
        "poolMeta": null,
        "mu": 4.07481,
        "sigma": 0.19309,
        "count": 1429,
        "outlier": false,
        "underlyingTokens": [
            "0xDA10009cBd5D07dd0CeCc66161FC93D7c9000da1"
        ],
        "il7d": null,
        "apyBase7d": null,
        "apyMean30d": 1.82542,
        "volumeUsd1d": null,
        "volumeUsd7d": null,
        "apyBaseInception": null
    },
    "c57bdc97-3100-41ff-845f-075363f6f5a4": {
        "chain": "Polygon",
        "project": "aave-v3",
        "symbol": "DAI",
        "tvlUsd": 1072456,
        "apyBase": 3.82699,
        "apyReward": null,
        "apy": 3.82699,
        "rewardTokens": null,
        "pool": "c57bdc97-3100-41ff-845f-075363f6f5a4",
        "apyPct1D": 0.08791,
        "apyPct7D": -0.46301,
        "apyPct30D": -1.46994,
        "stablecoin": true,
        "ilRisk": "no",
        "exposure": "single",
        "predictions": {
            "predictedClass": "Stable/Up",
            "predictedProbability": 56.99999999999999,
            "binnedConfidence": 1
        },
        "poolMeta": null,
        "mu": 4.4054,
        "sigma": 0.17587,
        "count": 1429,
        "outlier": false,
        "underlyingTokens": [
            "0x8f3Cf7ad23Cd3CaDbD9735AFf958023239c6A063"
        ],
        "il7d": null,
        "apyBase7d": null,
        "apyMean30d": 4.7252,
        "volumeUsd1d": null,
        "volumeUsd7d": null,
        "apyBaseInception": null
    },
    "517f3a7a-a3b0-4af9-be8e-bcb0fb549744": {
        "chain": "Ethereum",
        "project": "aave-v4",
        "symbol": "USDT",
        "tvlUsd": 990797,
        "apyBase": 3.28324,
        "apyReward": null,
        "apy": 3.28324,
        "rewardTokens": null,
        "pool": "517f3a7a-a3b0-4af9-be8e-bcb0fb549744",
        "apyPct1D": 0.233,
        "apyPct7D": 0.20239,
        "apyPct30D": 1.13256,
        "stablecoin": true,
        "ilRisk": "no",
        "exposure": "single",
        "predictions": {
            "predictedClass": "Down",
            "predictedProbability": 75,
            "binnedConfidence": 3
        },
        "poolMeta": "Core",
        "mu": 2.29187,
        "sigma": 0.06614,
        "count": 106,
        "outlier": false,
        "underlyingTokens": [
            "0xdAC17F958D2ee523a2206206994597C13D831ec7"
        ],
        "il7d": null,
        "apyBase7d": null,
        "apyMean30d": 2.35395,
        "volumeUsd1d": null,
        "volumeUsd7d": null,
        "apyBaseInception": null
    },
    "24762515-822a-46af-927c-77a1dc449bd0": {
        "chain": "OP Mainnet",
        "project": "aave-v3",
        "symbol": "USDC",
        "tvlUsd": 913303,
        "apyBase": 0.35642,
        "apyReward": null,
        "apy": 0.35642,
        "rewardTokens": null,
        "pool": "24762515-822a-46af-927c-77a1dc449bd0",
        "apyPct1D": 7e-05,
        "apyPct7D": 0.00058,
        "apyPct30D": 0.00488,
        "stablecoin": true,
        "ilRisk": "no",
        "exposure": "single",
        "predictions": {
            "predictedClass": "Stable/Up",
            "predictedProbability": 86,
            "binnedConfidence": 3
        },
        "poolMeta": null,
        "mu": 3.3252,
        "sigma": 0.16014,
        "count": 1429,
        "outlier": false,
        "underlyingTokens": [
            "0x7F5c764cBc14f9669B88837ca1490cCa17c31607"
        ],
        "il7d": null,
        "apyBase7d": null,
        "apyMean30d": 0.35389,
        "volumeUsd1d": null,
        "volumeUsd7d": null,
        "apyBaseInception": null
    },
    "09f4aa6a-f06b-4635-ada0-5f0e334d41f0": {
        "chain": "Aptos",
        "project": "aave-v3",
        "symbol": "USDT",
        "tvlUsd": 721893,
        "apyBase": 1.39346,
        "apyReward": null,
        "apy": 1.39346,
        "rewardTokens": null,
        "pool": "09f4aa6a-f06b-4635-ada0-5f0e334d41f0",
        "apyPct1D": 0.06094,
        "apyPct7D": 0.16249,
        "apyPct30D": -0.3087,
        "stablecoin": true,
        "ilRisk": "no",
        "exposure": "single",
        "predictions": {
            "predictedClass": "Stable/Up",
            "predictedProbability": 70,
            "binnedConfidence": 2
        },
        "poolMeta": null,
        "mu": 1.44704,
        "sigma": 0.0497,
        "count": 118,
        "outlier": false,
        "underlyingTokens": [
            "0x357b0b74bc833e95a115ad22604854d6b0fca151cecd94111770e5d6ffc9dc2b"
        ],
        "il7d": null,
        "apyBase7d": null,
        "apyMean30d": 1.30082,
        "volumeUsd1d": null,
        "volumeUsd7d": null,
        "apyBaseInception": null
    },
    "e68ecfb4-ba44-49e9-9626-31299405b520": {
        "chain": "Linea",
        "project": "aave-v3",
        "symbol": "WBTC",
        "tvlUsd": 704295,
        "apyBase": 0.08264,
        "apyReward": null,
        "apy": 0.08264,
        "rewardTokens": null,
        "pool": "e68ecfb4-ba44-49e9-9626-31299405b520",
        "apyPct1D": 0.01288,
        "apyPct7D": 0.01206,
        "apyPct30D": 0.0364,
        "stablecoin": false,
        "ilRisk": "no",
        "exposure": "single",
        "predictions": {
            "predictedClass": "Down",
            "predictedProbability": 57.99999999999999,
            "binnedConfidence": 1
        },
        "poolMeta": null,
        "mu": 0.05018,
        "sigma": 0.00387,
        "count": 491,
        "outlier": false,
        "underlyingTokens": [
            "0x3aAB2285ddcDdaD8edf438C1bAB47e1a9D05a9b4"
        ],
        "il7d": null,
        "apyBase7d": null,
        "apyMean30d": 0.0575,
        "volumeUsd1d": null,
        "volumeUsd7d": null,
        "apyBaseInception": null
    },
    "37b04faa-95bb-4ccb-9c4e-c70fa167342b": {
        "chain": "Polygon",
        "project": "aave-v3",
        "symbol": "USDC",
        "tvlUsd": 610760,
        "apyBase": 3.03767,
        "apyReward": null,
        "apy": 3.03767,
        "rewardTokens": null,
        "pool": "37b04faa-95bb-4ccb-9c4e-c70fa167342b",
        "apyPct1D": 0.0191,
        "apyPct7D": 0.1146,
        "apyPct30D": 0.17243,
        "stablecoin": true,
        "ilRisk": "no",
        "exposure": "single",
        "predictions": {
            "predictedClass": "Stable/Up",
            "predictedProbability": 77,
            "binnedConfidence": 3
        },
        "poolMeta": null,
        "mu": 3.9386,
        "sigma": 0.17128,
        "count": 1429,
        "outlier": false,
        "underlyingTokens": [
            "0x2791Bca1f2de4661ED88A30C99A7a9449Aa84174"
        ],
        "il7d": null,
        "apyBase7d": null,
        "apyMean30d": 2.92715,
        "volumeUsd1d": null,
        "volumeUsd7d": null,
        "apyBaseInception": null
    },
    "bde08c85-41c5-4d80-9bb1-0835a4352efa": {
        "chain": "OP Mainnet",
        "project": "aave-v3",
        "symbol": "USDT",
        "tvlUsd": 496824,
        "apyBase": 3.09852,
        "apyReward": null,
        "apy": 3.09852,
        "rewardTokens": null,
        "pool": "bde08c85-41c5-4d80-9bb1-0835a4352efa",
        "apyPct1D": -0.07558,
        "apyPct7D": 0.15264,
        "apyPct30D": 0.37044,
        "stablecoin": true,
        "ilRisk": "no",
        "exposure": "single",
        "predictions": {
            "predictedClass": "Stable/Up",
            "predictedProbability": 55.00000000000001,
            "binnedConfidence": 1
        },
        "poolMeta": null,
        "mu": 4.85948,
        "sigma": 0.21145,
        "count": 1429,
        "outlier": false,
        "underlyingTokens": [
            "0x94b008aA00579c1307B0EF2c499aD98a8ce58e58"
        ],
        "il7d": null,
        "apyBase7d": null,
        "apyMean30d": 2.78201,
        "volumeUsd1d": null,
        "volumeUsd7d": null,
        "apyBaseInception": null
    },
    "4ac1a968-68ab-4da8-87e3-8f1e15e3dae2": {
        "chain": "Ethereum",
        "project": "aave-v4",
        "symbol": "USDC",
        "tvlUsd": 410036,
        "apyBase": 7.48198,
        "apyReward": null,
        "apy": 7.48198,
        "rewardTokens": null,
        "pool": "4ac1a968-68ab-4da8-87e3-8f1e15e3dae2",
        "apyPct1D": 4.67088,
        "apyPct7D": 4.81787,
        "apyPct30D": 4.45009,
        "stablecoin": true,
        "ilRisk": "no",
        "exposure": "single",
        "predictions": {
            "predictedClass": "Down",
            "predictedProbability": 59,
            "binnedConfidence": 1
        },
        "poolMeta": "Core",
        "mu": 3.44856,
        "sigma": 0.13325,
        "count": 106,
        "outlier": false,
        "underlyingTokens": [
            "0xA0b86991c6218b36c1d19D4a2e9Eb0cE3606eB48"
        ],
        "il7d": null,
        "apyBase7d": null,
        "apyMean30d": 3.81984,
        "volumeUsd1d": null,
        "volumeUsd7d": null,
        "apyBaseInception": null
    },
    "38f1474f-bb56-46ff-b2c6-bc07539a1f2b": {
        "chain": "Ethereum",
        "project": "aave-v4",
        "symbol": "USDC",
        "tvlUsd": 370442,
        "apyBase": 2.69574,
        "apyReward": null,
        "apy": 2.69574,
        "rewardTokens": null,
        "pool": "38f1474f-bb56-46ff-b2c6-bc07539a1f2b",
        "apyPct1D": 0.21954,
        "apyPct7D": -0.58091,
        "apyPct30D": -0.5532,
        "stablecoin": true,
        "ilRisk": "no",
        "exposure": "single",
        "predictions": {
            "predictedClass": "Down",
            "predictedProbability": 72,
            "binnedConfidence": 2
        },
        "poolMeta": "Prime",
        "mu": 2.51448,
        "sigma": 0.06352,
        "count": 106,
        "outlier": false,
        "underlyingTokens": [
            "0xA0b86991c6218b36c1d19D4a2e9Eb0cE3606eB48"
        ],
        "il7d": null,
        "apyBase7d": null,
        "apyMean30d": 3.15552,
        "volumeUsd1d": null,
        "volumeUsd7d": null,
        "apyBaseInception": null
    },
    "7aab7b0f-01c1-4467-bc0d-77826d870f19": {
        "chain": "Arbitrum",
        "project": "aave-v3",
        "symbol": "USDC",
        "tvlUsd": 205199,
        "apyBase": 3.74191,
        "apyReward": null,
        "apy": 3.74191,
        "rewardTokens": null,
        "pool": "7aab7b0f-01c1-4467-bc0d-77826d870f19",
        "apyPct1D": 0.0151,
        "apyPct7D": 0.15232,
        "apyPct30D": -0.35899,
        "stablecoin": true,
        "ilRisk": "no",
        "exposure": "single",
        "predictions": {
            "predictedClass": "Stable/Up",
            "predictedProbability": 57.99999999999999,
            "binnedConfidence": 1
        },
        "poolMeta": null,
        "mu": 3.67736,
        "sigma": 0.15945,
        "count": 1429,
        "outlier": false,
        "underlyingTokens": [
            "0xFF970A61A04b1cA14834A43f5dE4533eBDDB5CC8"
        ],
        "il7d": null,
        "apyBase7d": null,
        "apyMean30d": 3.89796,
        "volumeUsd1d": null,
        "volumeUsd7d": null,
        "apyBaseInception": null
    },
    "5a49dee1-344d-4b50-a167-8f5faab08752": {
        "chain": "Linea",
        "project": "aave-v3",
        "symbol": "USDC",
        "tvlUsd": 141741,
        "apyBase": 5.09545,
        "apyReward": null,
        "apy": 5.09545,
        "rewardTokens": null,
        "pool": "5a49dee1-344d-4b50-a167-8f5faab08752",
        "apyPct1D": 1.47631,
        "apyPct7D": 2.0702,
        "apyPct30D": 0.37373,
        "stablecoin": true,
        "ilRisk": "no",
        "exposure": "single",
        "predictions": {
            "predictedClass": "Down",
            "predictedProbability": 69,
            "binnedConfidence": 2
        },
        "poolMeta": null,
        "mu": 3.19593,
        "sigma": 0.08675,
        "count": 491,
        "outlier": false,
        "underlyingTokens": [
            "0x176211869cA2b568f2A7D4EE941E073a821EE1ff"
        ],
        "il7d": null,
        "apyBase7d": null,
        "apyMean30d": 3.86659,
        "volumeUsd1d": null,
        "volumeUsd7d": null,
        "apyBaseInception": null
    },
    "5aabda74-2635-4870-89ab-d45b67d934d7": {
        "chain": "Ethereum",
        "project": "aave-v4",
        "symbol": "USDT",
        "tvlUsd": 137188,
        "apyBase": 3.4376,
        "apyReward": null,
        "apy": 3.4376,
        "rewardTokens": null,
        "pool": "5aabda74-2635-4870-89ab-d45b67d934d7",
        "apyPct1D": 0.13952,
        "apyPct7D": 0.23276,
        "apyPct30D": 2.03753,
        "stablecoin": true,
        "ilRisk": "no",
        "exposure": "single",
        "predictions": {
            "predictedClass": "Down",
            "predictedProbability": 65,
            "binnedConfidence": 2
        },
        "poolMeta": "Prime",
        "mu": 2.32067,
        "sigma": 0.07216,
        "count": 106,
        "outlier": false,
        "underlyingTokens": [
            "0xdAC17F958D2ee523a2206206994597C13D831ec7"
        ],
        "il7d": null,
        "apyBase7d": null,
        "apyMean30d": 2.86957,
        "volumeUsd1d": null,
        "volumeUsd7d": null,
        "apyBaseInception": null
    },
    "ef3c9b8f-ff81-483b-a672-21356dddaa1d": {
        "chain": "Aptos",
        "project": "aave-v3",
        "symbol": "USDC",
        "tvlUsd": 124853,
        "apyBase": 0.49162,
        "apyReward": null,
        "apy": 0.49162,
        "rewardTokens": null,
        "pool": "ef3c9b8f-ff81-483b-a672-21356dddaa1d",
        "apyPct1D": -0.00491,
        "apyPct7D": 0.18992,
        "apyPct30D": 0.02298,
        "stablecoin": true,
        "ilRisk": "no",
        "exposure": "single",
        "predictions": {
            "predictedClass": "Stable/Up",
            "predictedProbability": 59,
            "binnedConfidence": 1
        },
        "poolMeta": null,
        "mu": 0.82552,
        "sigma": 0.04087,
        "count": 118,
        "outlier": false,
        "underlyingTokens": [
            "0xbae207659db88bea0cbead6da0ed00aac12edcdda169e591cd41c94180b46f3b"
        ],
        "il7d": null,
        "apyBase7d": null,
        "apyMean30d": 0.40309,
        "volumeUsd1d": null,
        "volumeUsd7d": null,
        "apyBaseInception": null
    },
    "8d4d3acb-e1bf-471a-8256-36b90a8f4d25": {
        "chain": "Arbitrum",
        "project": "aave-v3",
        "symbol": "FRAX",
        "tvlUsd": 120923,
        "apyBase": 0.4247,
        "apyReward": null,
        "apy": 0.4247,
        "rewardTokens": null,
        "pool": "8d4d3acb-e1bf-471a-8256-36b90a8f4d25",
        "apyPct1D": 0,
        "apyPct7D": 0,
        "apyPct30D": 0.00601,
        "stablecoin": true,
        "ilRisk": "no",
        "exposure": "single",
        "predictions": {
            "predictedClass": "Stable/Up",
            "predictedProbability": 67,
            "binnedConfidence": 2
        },
        "poolMeta": null,
        "mu": 4.36334,
        "sigma": 0.20932,
        "count": 989,
        "outlier": false,
        "underlyingTokens": [
            "0x17FC002b466eEc40DaE837Fc4bE5c67993ddBd6F"
        ],
        "il7d": null,
        "apyBase7d": null,
        "apyMean30d": 0.42338,
        "volumeUsd1d": null,
        "volumeUsd7d": null,
        "apyBaseInception": null
    },
    "363e5586-cfee-402c-9b0b-be70366052e8": {
        "chain": "OP Mainnet",
        "project": "aave-v3",
        "symbol": "DAI",
        "tvlUsd": 101170,
        "apyBase": 2.91319,
        "apyReward": null,
        "apy": 2.91319,
        "rewardTokens": null,
        "pool": "363e5586-cfee-402c-9b0b-be70366052e8",
        "apyPct1D": 0.00337,
        "apyPct7D": -0.05408,
        "apyPct30D": 0.04302,
        "stablecoin": true,
        "ilRisk": "no",
        "exposure": "single",
        "predictions": {
            "predictedClass": "Down",
            "predictedProbability": 54,
            "binnedConfidence": 1
        },
        "poolMeta": null,
        "mu": 4.00577,
        "sigma": 0.16914,
        "count": 1429,
        "outlier": false,
        "underlyingTokens": [
            "0xDA10009cBd5D07dd0CeCc66161FC93D7c9000da1"
        ],
        "il7d": null,
        "apyBase7d": null,
        "apyMean30d": 2.94133,
        "volumeUsd1d": null,
        "volumeUsd7d": null,
        "apyBaseInception": null
    },
    "21091399-1187-4242-8e03-9b06032f9a8f": {
        "chain": "Gnosis",
        "project": "aave-v3",
        "symbol": "WXDAI",
        "tvlUsd": 96229,
        "apyBase": 3.31563,
        "apyReward": null,
        "apy": 3.31563,
        "rewardTokens": null,
        "pool": "21091399-1187-4242-8e03-9b06032f9a8f",
        "apyPct1D": 0.31638,
        "apyPct7D": 0.94143,
        "apyPct30D": 2.40426,
        "stablecoin": true,
        "ilRisk": "no",
        "exposure": "single",
        "predictions": {
            "predictedClass": "Down",
            "predictedProbability": 60,
            "binnedConfidence": 1
        },
        "poolMeta": null,
        "mu": 4.04192,
        "sigma": 0.1213,
        "count": 899,
        "outlier": false,
        "underlyingTokens": [
            "0xe91D153E0b41518A2Ce8Dd3D7944Fa863463a97d"
        ],
        "il7d": null,
        "apyBase7d": null,
        "apyMean30d": 2.64062,
        "volumeUsd1d": null,
        "volumeUsd7d": null,
        "apyBaseInception": null
    },
    "78c4b5eb-6e36-4c3a-94b5-779e37dbf9a4": {
        "chain": "Celo",
        "project": "aave-v3",
        "symbol": "USDC",
        "tvlUsd": 65278,
        "apyBase": 1.50647,
        "apyReward": null,
        "apy": 1.50647,
        "rewardTokens": null,
        "pool": "78c4b5eb-6e36-4c3a-94b5-779e37dbf9a4",
        "apyPct1D": 0,
        "apyPct7D": 0.03323,
        "apyPct30D": -1.08841,
        "stablecoin": true,
        "ilRisk": "no",
        "exposure": "single",
        "predictions": {
            "predictedClass": "Stable/Up",
            "predictedProbability": 53,
            "binnedConfidence": 1
        },
        "poolMeta": null,
        "mu": 2.51132,
        "sigma": 0.12261,
        "count": 322,
        "outlier": false,
        "underlyingTokens": [
            "0xcebA9300f2b948710d2653dD7B07f33A8B32118C"
        ],
        "il7d": null,
        "apyBase7d": null,
        "apyMean30d": 2.485,
        "volumeUsd1d": null,
        "volumeUsd7d": null,
        "apyBaseInception": null
    },
    "a214e900-2bcd-431f-9744-632fa5436fee": {
        "chain": "Ethereum",
        "project": "aave-v3",
        "symbol": "SDAI",
        "tvlUsd": 50437,
        "apyBase": 0,
        "apyReward": null,
        "apy": 0,
        "rewardTokens": null,
        "pool": "a214e900-2bcd-431f-9744-632fa5436fee",
        "apyPct1D": 0,
        "apyPct7D": 0,
        "apyPct30D": 0,
        "stablecoin": true,
        "ilRisk": "no",
        "exposure": "single",
        "predictions": {
            "predictedClass": null,
            "predictedProbability": null,
            "binnedConfidence": null
        },
        "poolMeta": null,
        "mu": 0,
        "sigma": 0,
        "count": 1049,
        "outlier": false,
        "underlyingTokens": [
            "0x83F20F44975D03b1b09e64809B757c47f942BEeA"
        ],
        "il7d": null,
        "apyBase7d": null,
        "apyMean30d": 0,
        "volumeUsd1d": null,
        "volumeUsd7d": null,
        "apyBaseInception": null
    },
    "6817bab0-5389-40a0-84d1-78830c1d81aa": {
        "chain": "Linea",
        "project": "aave-v3",
        "symbol": "USDT",
        "tvlUsd": 36169,
        "apyBase": 6.33699,
        "apyReward": null,
        "apy": 6.33699,
        "rewardTokens": null,
        "pool": "6817bab0-5389-40a0-84d1-78830c1d81aa",
        "apyPct1D": -1.04253,
        "apyPct7D": 1.49536,
        "apyPct30D": 3.43471,
        "stablecoin": true,
        "ilRisk": "no",
        "exposure": "single",
        "predictions": {
            "predictedClass": "Down",
            "predictedProbability": 65,
            "binnedConfidence": 2
        },
        "poolMeta": null,
        "mu": 3.21356,
        "sigma": 0.09846,
        "count": 489,
        "outlier": false,
        "underlyingTokens": [
            "0xA219439258ca9da29E9Cc4cE5596924745e12B93"
        ],
        "il7d": null,
        "apyBase7d": null,
        "apyMean30d": 5.89615,
        "volumeUsd1d": null,
        "volumeUsd7d": null,
        "apyBaseInception": null
    },
    "4ef4eb9a-e22e-4190-b8f3-8c75373ad0d6": {
        "chain": "Ethereum",
        "project": "aave-v3",
        "symbol": "FRAX",
        "tvlUsd": 9891,
        "apyBase": 2.69819,
        "apyReward": null,
        "apy": 2.69819,
        "rewardTokens": null,
        "pool": "4ef4eb9a-e22e-4190-b8f3-8c75373ad0d6",
        "apyPct1D": null,
        "apyPct7D": 0.08639,
        "apyPct30D": 0.0896,
        "stablecoin": true,
        "ilRisk": "no",
        "exposure": "single",
        "predictions": {
            "predictedClass": "Down",
            "predictedProbability": 54,
            "binnedConfidence": 1
        },
        "poolMeta": null,
        "mu": 5.30783,
        "sigma": 0.30397,
        "count": 1048,
        "outlier": false,
        "underlyingTokens": [
            "0x853d955aCEf822Db058eb8505911ED77F175b99e"
        ],
        "il7d": null,
        "apyBase7d": null,
        "apyMean30d": 2.63102,
        "volumeUsd1d": null,
        "volumeUsd7d": null,
        "apyBaseInception": null
    }
}